Workbook

Sheet README
A1: Pet-проект: Аналитический пакет селлера на маркетплейсе
A4: Это учебный портфельный проект. Сценарий: я работаю маркетологом-аналитиком у селлера на маркетплейсе РФ (Wildberries / Ozon / Яндекс.Маркет). Ассортимент ~15 SKU из 5 категорий: товары для дома, косметика, спорт, электроника-аксессуары, канцелярия. Задача — разобраться в данных, понять, что работает, что нет, и куда расти. Все цифры синтетические; методология, формулы и структура листов рабочие — переносятся на реальный датасет за 1–2 дня.
A7: 1. Мониторинг цен конкурентов: сравнение нашего магазина с другими селлерами за 8 недель.
A8: 2. Выбор поставщика: скоринговая модель с весами по 10 параметрам.
A9: 3. Ассортимент: ABC по выручке + XYZ по стабильности → матрица 3×3 с готовыми стратегиями.
A10: 4. Юнит-экономика: цена / COGS / маржа / контрибуция / BEP по каждому SKU.
A11: 5. Запуск новой категории: 5-летняя ROI-модель с NPV, IRR, payback и таблицей чувствительности.
A12: 6. Сезонность: помесячные коэффициенты по категориям + прогноз на следующий период.
A13: 7. Gap-анализ: где в ассортименте дыры по категориям с высоким спросом на маркетплейсе.
A14: 8. Бенчмарк рынков: что взять с e-commerce практик РФ / Китая / США / ЕС / Турции.
A15: 9. Дашборд: KPI-сводка для руководителя на одном экране.
A18: 1) Каждый лист отвечает на бизнес-вопрос, а не просто визуализирует данные.
... A39: Автор: подготовлено как учебный pet-проект.

Sheet 01_Цены_конкурентов
A1: 01. Мониторинг цен у конкурирующих селлеров/площадок
A2: Источник: парсер карточек товаров на WB / Ozon / Я.Маркет (n8n + LLM-нормализация). Здесь — последние 8 недель по 3 ключевым SKU.
A5: Подушка ортопедическая 50×70 (₽/шт)
A6: Площадка / селлер | B6: 01.09.25 | C6: 08.09.25 | D6: 15.09.25 | E6: 22.09.25 | F6: 29.09.25 | G6: 06.10.25 | H6: 13.10.25 | I6: 20.10.25 | J6: Avg 8 нед. | K6: Δ нед. | L6: Индекс к нашему
A7: Наш магазин | B7: 1497 | C7: 1513 | D7: 1499 | E7: 1468 | F7: 1453 | G7: 1577 | H7: 1534 | I7: 1479 | J7: =AVERAGE(B7:I7) -> 1502.5 | K7: =(I7/H7)-1 -> -0.035853977 | L7: =I7/I7 -> 1
A8: Wildberries TOP-1 | B8: 1607 | C8: 1567 | D8: 1668 | E8: 1703 | F8: 1593 | G8: 1593 | H8: 1596 | I8: 1667 | J8: =AVERAGE(B8:I8) -> 1624.25 | K8: =(I8/H8)-1 -> 0.044486216 | L8: =I8/I7 -> 1.1271129
A9: Ozon TOP-1 | B9: 1615 | C9: 1548 | D9: 1553 | E9: 1626 | F9: 1667 | G9: 1668 | H9: 1636 | I9: 1679 | J9: =AVERAGE(B9:I9) -> 1624 | K9: =(I9/H9)-1 -> 0.026283619 | L9: =I9/I7 -> 1.1352265
A10: Яндекс.Маркет TOP-1 | B10: 1670 | C10: 1753 | D10: 1717 | E10: 1717 | F10: 1677 | G10: 1688 | H10: 1666 | I10: 1777 | J10: =AVERAGE(B10:I10) -> 1708.125 | K10: =(I10/H10)-1 -> 0.066626651 | L10: =I10/I7 -> 1.2014875
A11: Сбермегамаркет | B11: 1757 | C11: 1738 | D11: 1833 | E11: 1765 | F11: 1746 | G11: 1830 | H11: 1803 | I11: 1845 | J11: =AVERAGE(B11:I11) -> 1789.625 | K11: =(I11/H11)-1 -> 0.023294509 | L11: =I11/I7 -> 1.2474645
A12: AliExpress (импорт) | B12: 1173 | C12: 1190 | D12: 1228 | E12: 1200 | F12: 1227 | G12: 1239 | H12: 1225 | I12: 1238 | J12: =AVERAGE(B12:I12) -> 1215 | K12: =(I12/H12)-1 -> 0.010612245 | L12: =I12/I7 -> 0.83705206
A15: Гантели разборные 10 кг (пара) (₽/комплект)
A16: Площадка / селлер | B16: 01.09.25 | C16: 08.09.25 | D16: 15.09.25 | E16: 22.09.25 | F16: 29.09.25 | G16: 06.10.25 | H16: 13.10.25 | I16: 20.10.25 | J16: Avg 8 нед. | K16: Δ нед. | L16: Индекс к нашему
A17: Наш магазин | B17: 4018 | C17: 4089 | D17: 4136 | E17: 4148 | F17: 4003 | G17: 4084 | H17: 4118 | I17: 3990 | J17: =AVERAGE(B17:I17) -> 4073.25 | K17: =(I17/H17)-1 -> -0.03108305 | L17: =I17/I17 -> 1
A18: Wildberries TOP-1 | B18: 4214 | C18: 4249 | D18: 4276 | E18: 4362 | F18: 4417 | G18: 4297 | H18: 4314 | I18: 4459 | J18: =AVERAGE(B18:I18) -> 4323.5 | K18: =(I18/H18)-1 -> 0.033611497 | L18: =I18/I17 -> 1.1175439
A19: Ozon TOP-1 | B19: 4033 | C19: 4117 | D19: 4260 | E19: 4241 | F19: 4321 | G19: 4246 | H19: 4274 | I19: 4267 | J19: =AVERAGE(B19:I19) -> 4219.875 | K19: =(I19/H19)-1 -> -0.00163781 | L19: =I19/I17 -> 1.0694236
A20: Яндекс.Маркет TOP-1 | B20: 4310 | C20: 4313 | D20: 4296 | E20: 4433 | F20: 4421 | G20: 4463 | H20: 4521 | I20: 4367 | J20: =AVERAGE(B20:I20) -> 4390.5 | K20: =(I20/H20)-1 -> -0.03406326 | L20: =I20/I17 -> 1.0944862
A21: Сбермегамаркет | B21: 4384 | C21: 4379 | D21: 4505 | E21: 4570 | F21: 4658 | G21: 4491 | H21: 4418 | I21: 4646 | J21: =AVERAGE(B21:I21) -> 4506.375 | K21: =(I21/H21)-1 -> 0.051607062 | L21: =I21/I17 -> 1.164411
A22: AliExpress (импорт) | B22: 4673 | C22: 4672 | D22: 4702 | E22: 4918 | F22: 4957 | G22: 4792 | H22: 5065 | I22: 4781 | J22: =AVERAGE(B22:I22) -> 4820 | K22: =(I22/H22)-1 -> -0.056071076 | L22: =I22/I17 -> 1.1982456
A25: Кабель USB-C → USB-C, 1 м (₽/шт)
A26: Площадка / селлер | B26: 01.09.25 | C26: 08.09.25 | D26: 15.09.25 | E26: 22.09.25 | F26: 29.09.25 | G26: 06.10.25 | H26: 13.10.25 | I26: 20.10.25 | J26: Avg 8 нед. | K26: Δ нед. | L26: Индекс к нашему
A27: Наш магазин | B27: 293 | C27: 297 | D27: 284 | E27: 304 | F27: 288 | G27: 302 | H27: 304 | I27: 288 | J27: =AVERAGE(B27:I27) -> 295 | K27: =(I27/H27)-1 -> -0.052631579 | L27: =I27/I27 -> 1
A28: Wildberries TOP-1 | B28: 320 | C28: 315 | D28: 320 | E28: 332 | F28: 333 | G28: 331 | H28: 330 | I28: 322 | J28: =AVERAGE(B28:I28) -> 325.375 | K28: =(I28/H28)-1 -> -0.024242424 | L28: =I28/I27 -> 1.1180556
A29: Ozon TOP-1 | B29: 320 | C29: 308 | D29: 318 | E29: 314 | F29: 312 | G29: 316 | H29: 311 | I29: 308 | J29: =AVERAGE(B29:I29) -> 313.375 | K29: =(I29/H29)-1 -> -0.0096463023 | L29: =I29/I27 -> 1.0694444
A30: Яндекс.Маркет TOP-1 | B30: 362 | C30: 346 | D30: 353 | E30: 358 | F30: 359 | G30: 355 | H30: 354 | I30: 368 | J30: =AVERAGE(B30:I30) -> 356.875 | K30: =(I30/H30)-1 -> 0.039548023 | L30: =I30/I27 -> 1.2777778
A31: Сбермегамаркет | B31: 393 | C31: 395 | D31: 394 | E31: 373 | F31: 396 | G31: 381 | H31: 396 | I31: 389 | J31: =AVERAGE(B31:I31) -> 389.625 | K31: =(I31/H31)-1 -> -0.017676768 | L31: =I31/I27 -> 1.3506944
A32: AliExpress (импорт) | B32: 194 | C32: 200 | D32: 194 | E32: 196 | F32: 200 | G32: 208 | H32: 197 | I32: 210 | J32: =AVERAGE(B32:I32) -> 199.875 | K32: =(I32/H32)-1 -> 0.065989848 | L32: =I32/I27 -> 0.72916667
A35: Вывод и рекомендация
A36: 1. По подушке наш магазин держит средний минимум по площадкам РФ (−8% к ТОП-1 WB). Импортный AliExpress дешевле −20%, но без гарантии доставки и возврата по закону РФ → реальный риск переключения клиентов = низкий.
A37: 2. По гантелям мы дешевле всех площадок РФ, но AliExpress дороже на ~20%. Это важный аргумент для карточки: «российский склад, доставка 1 день».
A38: 3. По USB-C кабелю мы держим средний рынок РФ, AliExpress дешевле на 30% — здесь импорт реально съедает спрос. Рекомендация: продвигать наш кабель через категорию «российская гарантия 12 мес.» в карточке.
A39: 4. Цены растут ~0.4%/нед. (см. столбец Δ нед.). По топ-3 SKU стоит зафиксировать цену до 30.11 — рынок индексируется вверх вместе с ослаблением рубля.

Sheet 02_Сравнение_поставщиков
A1: 02. Сравнение поставщиков — скоринговая модель
A2: Цель: на основе 10 параметров выбрать поставщика для масштабирования закупки топовых SKU. Веса параметров согласовываются с руководителем — модель пересчитывается.
A4: Веса параметров (Σ = 100%)
A5: Параметр | B5: Вес
A6: Цена / себестоимость | B6: 0.2
A7: Качество (рейтинг отзывов) | B7: 0.15
A8: Минимальная партия (MOQ) | B8: 0.1
A9: Срок поставки | B9: 0.1
A10: Условия оплаты | B10: 0.07
A11: Сертификация / документы | B11: 0.1
A12: Логистика (склады РФ) | B12: 0.1
A13: Гибкость (возвраты, кастом) | B13: 0.05
A14: Опыт работы с маркетплейсами РФ | B14: 0.08
A15: Тех. поддержка / коммуникация | B15: 0.05
A17: Параметры по поставщикам (заполняются по запросу КП и из открытых источников)
A18: Поставщик | B18: Цена (отн., 100 = базовая) | C18: Рейтинг (1-5) | D18: MOQ (шт) | E18: Срок (дней) | F18: Оплата | G18: Сертиф. | H18: Склады РФ | I18: Гибкость | J18: Опыт МП | K18: Тех. поддержка | L18: Сводный балл | M18: Ранг
A19: Турецкая фабрика TR-Home | B19: 100 | C19: 4.6 | D19: 500 | E19: 28 | F19: 4 | G19: 5 | H19: 3 | I19: 4 | J19: 4 | K19: 4 | L19: =(MIN($B$19:$B$24)/B19)*$B$6+(C19/5)*$B$7+(MIN($D$19:$D$24)/D19)*$B$8+(MIN($E$19:$E$24)/E19)*$B$9+(F19/5)*$B$10+(G19/5)*$B$11+(H19/5)*$B$12+(I19/5)*$B$13+(J19/5)*$B$14+(K19/5)*$B$15 -> 0.68185714 | M19: =RANK(L19,$L$19:$L$24) -> 4
A20: Китайский завод CN-Bulk | B20: 78 | C20: 4.2 | D20: 1000 | E20: 45 | F20: 3 | G20: 4 | H20: 2 | I20: 3 | J20: 5 | K20: 3 | L20: =(MIN($B$19:$B$24)/B20)*$B$6+(C20/5)*$B$7+(MIN($D$19:$D$24)/D20)*$B$8+(MIN($E$19:$E$24)/E20)*$B$9+(F20/5)*$B$10+(G20/5)*$B$11+(H20/5)*$B$12+(I20/5)*$B$13+(J20/5)*$B$14+(K20/5)*$B$15 -> 0.64411111 | M20: =RANK(L20,$L$19:$L$24) -> 5
A21: Российская фабрика RU-Plant | B21: 115 | C21: 4.3 | D21: 200 | E21: 10 | F21: 5 | G21: 5 | H21: 5 | I21: 5 | J21: 5 | K21: 5 | L21: =(MIN($B$19:$B$24)/B21)*$B$6+(C21/5)*$B$7+(MIN($D$19:$D$24)/D21)*$B$8+(MIN($E$19:$E$24)/E21)*$B$9+(F21/5)*$B$10+(G21/5)*$B$11+(H21/5)*$B$12+(I21/5)*$B$13+(J21/5)*$B$14+(K21/5)*$B$15 -> 0.78965217 | M21: =RANK(L21,$L$19:$L$24) -> 3
A22: Узбекский поставщик UZ-Home | B22: 92 | C22: 4 | D22: 300 | E22: 21 | F22: 4 | G22: 3 | H22: 3 | I22: 4 | J22: 3 | K22: 3 | L22: =(MIN($B$19:$B$24)/B22)*$B$6+(C22/5)*$B$7+(MIN($D$19:$D$24)/D22)*$B$8+(MIN($E$19:$E$24)/E22)*$B$9+(F22/5)*$B$10+(G22/5)*$B$11+(H22/5)*$B$12+(I22/5)*$B$13+(J22/5)*$B$14+(K22/5)*$B$15 -> 0.62404141 | M22: =RANK(L22,$L$19:$L$24) -> 6
A23: Беларусский дистрибьютор BY | B23: 108 | C23: 4.4 | D23: 100 | E23: 7 | F23: 5 | G23: 5 | H23: 4 | I23: 5 | J23: 4 | K23: 4 | L23: =(MIN($B$19:$B$24)/B23)*$B$6+(C23/5)*$B$7+(MIN($D$19:$D$24)/D23)*$B$8+(MIN($E$19:$E$24)/E23)*$B$9+(F23/5)*$B$10+(G23/5)*$B$11+(H23/5)*$B$12+(I23/5)*$B$13+(J23/5)*$B$14+(K23/5)*$B$15 -> 0.80187302 | M23: =RANK(L23,$L$19:$L$24) -> 2
A24: Локальный OEM RU-OEM | B24: 125 | C24: 4.5 | D24: 50 | E24: 5 | F24: 5 | G24: 5 | H24: 5 | I24: 5 | J24: 4 | K24: 5 | L24: =(MIN($B$19:$B$24)/B24)*$B$6+(C24/5)*$B$7+(MIN($D$19:$D$24)/D24)*$B$8+(MIN($E$19:$E$24)/E24)*$B$9+(F24/5)*$B$10+(G24/5)*$B$11+(H24/5)*$B$12+(I24/5)*$B$13+(J24/5)*$B$14+(K24/5)*$B$15 -> 0.8938 | M24: =RANK(L24,$L$19:$L$24) -> 1
A27: Вывод и рекомендация
A28: 1. Российская фабрика RU-Plant и Беларусский дистрибьютор BY — лидеры по сводному баллу. Они дороже Китая на 10-15%, но компенсируют это сертификацией, складами в РФ и сроками поставки в разы быстрее.
A29: 2. Китайский завод CN-Bulk — самый дешёвый по цене, но MOQ 1000 шт и срок 45 дней делают его невыгодным для нашей ниши быстрой ротации.
A30: 3. Локальный OEM RU-OEM — премиум-вариант для топовых SKU класса A (см. лист 03). Подходит для запуска собственного бренда, но цена на 25% выше базовой.
A31: 4. Рекомендация: для категорий «товары для дома» и «канцелярия» — RU-Plant; для электроники-аксессуаров — CN-Bulk (т.к. цена решает); для премиум-линеек — RU-OEM. Веса можно пересмотреть с руководителем под другую стратегию.

Sheet 03_ABC_анализ
A1: 03. ABC-анализ ассортимента по выручке за 12 мес.
A2: Метод: сортируем SKU по убыванию выручки → накопительная доля. A: ≤ 80%, B: 80–95%, C: > 95%. Это «кто делает кассу».
A4: # | B4: SKU | C4: Категория | D4: Выручка / год | E4: Доля в выручке | F4: Накопит. доля | G4: Класс ABC
A5: 1 | B5: Подушка ортопедическая 50×70 | C5: Товары для дома | D5: 4850000 | E5: =D5/$D$20 -> 0.17364841 | F5: =E5 -> 0.17364841 | G5: =IF(F5<=0.8,"A",IF(F5<=0.95,"B","C")) -> A
A6: 2 | B6: Набор постельного белья евро | C6: Товары для дома | D6: 3920000 | E6: =D6/$D$20 -> 0.14035088 | F6: =F5+E6 -> 0.31399928 | G6: =IF(F6<=0.8,"A",IF(F6<=0.95,"B","C")) -> A
A7: 3 | B7: Гантели разборные 10 кг | C7: Спорт | D7: 3410000 | E7: =D7/$D$20 -> 0.12209094 | F7: =F6+E7 -> 0.43609023 | G7: =IF(F7<=0.8,"A",IF(F7<=0.95,"B","C")) -> A
A8: 4 | B8: Кофеварка капельная KS-200 | C8: Товары для дома | D8: 2980000 | E8: =D8/$D$20 -> 0.10669531 | F8: =F7+E8 -> 0.54278554 | G8: =IF(F8<=0.8,"A",IF(F8<=0.95,"B","C")) -> A
A9: 5 | B9: Шампунь увлажняющий 400 мл | C9: Косметика и уход | D9: 2540000 | E9: =D9/$D$20 -> 0.09094164 | F9: =F8+E9 -> 0.63372718 | G9: =IF(F9<=0.8,"A",IF(F9<=0.95,"B","C")) -> A
A10: 6 | B10: Наушники TWS базовые | C10: Электроника-акс. | D10: 2120000 | E10: =D10/$D$20 -> 0.075904046 | F10: =F9+E10 -> 0.70963122 | G10: =IF(F10<=0.8,"A",IF(F10<=0.95,"B","C")) -> A
A11: 7 | B11: Коврик для йоги 6 мм | C11: Спорт | D11: 1830000 | E11: =D11/$D$20 -> 0.065520945 | F11: =F10+E11 -> 0.77515217 | G11: =IF(F11<=0.8,"A",IF(F11<=0.95,"B","C")) -> A
A12: 8 | B12: Кабель USB-C → USB-C, 1 м | C12: Электроника-акс. | D12: 1640000 | E12: =D12/$D$20 -> 0.058718224 | F12: =F11+E12 -> 0.83387039 | G12: =IF(F12<=0.8,"A",IF(F12<=0.95,"B","C")) -> B
A13: 9 | B13: Колонка Bluetooth портативная | C13: Электроника-акс. | D13: 1350000 | E13: =D13/$D$20 -> 0.048335124 | F13: =F12+E13 -> 0.88220551 | G13: =IF(F13<=0.8,"A",IF(F13<=0.95,"B","C")) -> B
A14: 10 | B14: Крем для лица 50 мл | C14: Косметика и уход | D14: 1120000 | E14: =D14/$D$20 -> 0.040100251 | F14: =F13+E14 -> 0.92230576 | G14: =IF(F14<=0.8,"A",IF(F14<=0.95,"B","C")) -> B
A15: 11 | B15: Ежедневник А5 датированный | C15: Канцелярия | D15: 780000 | E15: =D15/$D$20 -> 0.02792696 | F15: =F14+E15 -> 0.95023272 | G15: =IF(F15<=0.8,"A",IF(F15<=0.95,"B","C")) -> C
A16: 12 | B16: Эспандер кистевой пара | C16: Спорт | D16: 540000 | E16: =D16/$D$20 -> 0.019334049 | F16: =F15+E16 -> 0.96956677 | G16: =IF(F16<=0.8,"A",IF(F16<=0.95,"B","C")) -> C
A17: 13 | B17: Парфюм женский 50 мл | C17: Косметика и уход | D17: 410000 | E17: =D17/$D$20 -> 0.014679556 | F17: =F16+E17 -> 0.98424633 | G17: =IF(F17<=0.8,"A",IF(F17<=0.95,"B","C")) -> C
... A19: 15 | B19: Набор маркеров 12 цветов | C19: Канцелярия | D19: 160000 | E19: =D19/$D$20 -> 0.0057286072 | F19: =F18+E19 -> 1 | G19: =IF(F19<=0.8,"A",IF(F19<=0.95,"B","C")) -> C
B20: ИТОГО: | D20: =SUM(D5:D19) -> 27930000
A22: Вывод и рекомендация
A23: 1. ТОП-5 SKU делают ~63% выручки, а ТОП-7 уже ~78%. Это «золотой запас» — приоритет складского запаса, минимум промо-агрессии (не «выжигаем» маржу), контракты с поставщиком RU-Plant на годовые объёмы.
A24: 2. SKU класса C (мелкие позиции 11-15) дают <5% выручки, но занимают место в ассортименте. Кандидаты на ревизию: либо они «long tail» лояльной аудитории, либо выводим из ассортимента и освобождаем ресурсы.
A25: 3. Категория «Косметика и уход» равномерно распределена по классам A-B-C — сбалансированная категория. Категория «Электроника-аксессуары» концентрируется в B → точка роста, если пойти в премиум.
A26: 4. Без XYZ-анализа ABC обманчив: SKU класса A может быть «угасающей звездой». Смотрим парно — лист 04 → лист 05.

Sheet 04_XYZ_анализ
A1: 04. XYZ-анализ — стабильность спроса по SKU
A2: Метод: помесячные продажи за 12 мес. → СКО / Среднее = коэффициент вариации (CV). X: CV < 10%, Y: 10–25%, Z: > 25%.
A4: SKU | B4: Янв | C4: Фев | D4: Мар | E4: Апр | F4: Май | G4: Июн | H4: Июл | I4: Авг | J4: Сен | K4: Окт | L4: Ноя | M4: Дек | N4: Среднее | O4: СКО | P4: CV | Q4: Класс XYZ | R4: Категория
A5: Подушка ортопедическая 50×70 | B5: 361251.21 | C5: 308647.44 | D5: 392563.95 | E5: 388367.67 | F5: 376419.85 | G5: 354900.82 | H5: 350896.43 | I5: 347967.47 | J5: 369799.57 | K5: 401680.51 | L5: 578940.97 | M5: 591996.75 | N5: =AVERAGE(B5:M5) -> 401952.72 | O5: =STDEV(B5:M5) -> 89187.048 | P5: =O5/N5 -> 0.22188443 | Q5: =IF(P5<0.1,"X",IF(P5<0.25,"Y","Z")) -> Y | R5: Товары для дома
A6: Набор постельного белья евро | B6: 284830.48 | C6: 254556.8 | D6: 301616.18 | E6: 303552.45 | F6: 325295.53 | G6: 292551.56 | H6: 291068.35 | I6: 294180.01 | J6: 293743.12 | K6: 323384.48 | L6: 475454.47 | M6: 491904.51 | N6: =AVERAGE(B6:M6) -> 327678.16 | O6: =STDEV(B6:M6) -> 75150.786 | P6: =O6/N6 -> 0.22934329 | Q6: =IF(P6<0.1,"X",IF(P6<0.25,"Y","Z")) -> Y | R6: Товары для дома
A7: Гантели разборные 10 кг | B7: 407881.11 | C7: 367908.46 | D7: 326647.82 | E7: 326996.49 | F7: 317451.38 | G7: 295379.76 | H7: 295265.64 | I7: 238637.28 | J7: 223235.8 | K7: 228468.37 | L7: 216114.59 | M7: 177554.14 | N7: =AVERAGE(B7:M7) -> 285128.4 | O7: =STDEV(B7:M7) -> 68879.21 | P7: =O7/N7 -> 0.2415726 | Q7: =IF(P7<0.1,"X",IF(P7<0.25,"Y","Z")) -> Y | R7: Спорт
A8: Кофеварка капельная KS-200 | B8: 205710.36 | C8: 206084.27 | D8: 247599.2 | E8: 248159.22 | F8: 233859.87 | G8: 224670.26 | H8: 221106.26 | I8: 204836.93 | J8: 231291.68 | K8: 256575.46 | L8: 371260.99 | M8: 339665.5 | N8: =AVERAGE(B8:M8) -> 249235 | O8: =STDEV(B8:M8) -> 52920.447 | P8: =O8/N8 -> 0.21233152 | Q8: =IF(P8<0.1,"X",IF(P8<0.25,"Y","Z")) -> Y | R8: Товары для дома
A9: Шампунь увлажняющий 400 мл | B9: 212789.69 | C9: 207546.63 | D9: 251331.8 | E9: 194875.06 | F9: 187488.94 | G9: 174008.28 | H9: 183813.15 | I9: 144536.93 | J9: 191614.05 | K9: 186067.49 | L9: 223275.26 | M9: 318759.35 | N9: =AVERAGE(B9:M9) -> 206342.22 | O9: =STDEV(B9:M9) -> 44188.936 | P9: =O9/N9 -> 0.21415364 | Q9: =IF(P9<0.1,"X",IF(P9<0.25,"Y","Z")) -> Y | R9: Косметика и уход
A10: Наушники TWS базовые | B10: 175170.18 | C10: 178345.44 | D10: 159295.98 | E10: 174661.33 | F10: 147644.15 | G10: 183277.92 | H10: 145199.94 | I10: 159402.8 | J10: 160454.96 | K10: 169986.38 | L10: 263780.55 | M10: 175972.3 | N10: =AVERAGE(B10:M10) -> 174432.66 | O10: =STDEV(B10:M10) -> 30632.57 | P10: =O10/N10 -> 0.17561258 | Q10: =IF(P10<0.1,"X",IF(P10<0.25,"Y","Z")) -> Y | R10: Электроника-акс.
A11: Коврик для йоги 6 мм | B11: 219745.21 | C11: 184569.72 | D11: 160540.29 | E11: 167678.57 | F11: 166722.13 | G11: 171231.81 | H11: 140660.56 | I11: 133402.2 | J11: 137493.7 | K11: 126761.22 | L11: 135076.18 | M11: 83111.045 | N11: =AVERAGE(B11:M11) -> 152249.39 | O11: =STDEV(B11:M11) -> 34256.792 | P11: =O11/N11 -> 0.22500447 | Q11: =IF(P11<0.1,"X",IF(P11<0.25,"Y","Z")) -> Y | R11: Спорт
A12: Кабель USB-C → USB-C, 1 м | B12: 136093.55 | C12: 133326.42 | D12: 121010.44 | E12: 127095.43 | F12: 130858.69 | G12: 117458.89 | H12: 120690.65 | I12: 115140.48 | J12: 119995.86 | K12: 137203.73 | L12: 244114.3 | M12: 143375.49 | N12: =AVERAGE(B12:M12) -> 137196.99 | O12: =STDEV(B12:M12) -> 34816.825 | P12: =O12/N12 -> 0.25377251 | Q12: =IF(P12<0.1,"X",IF(P12<0.25,"Y","Z")) -> Z | R12: Электроника-акс.
A13: Колонка Bluetooth портативная | B13: 106599.62 | C13: 98382.828 | D13: 94405.553 | E13: 101298.18 | F13: 93627.193 | G13: 102751.83 | H13: 86877.327 | I13: 85035.838 | J13: 115082.59 | K13: 98324.824 | L13: 208407.29 | M13: 137312.81 | N13: =AVERAGE(B13:M13) -> 110675.49 | O13: =STDEV(B13:M13) -> 33751.166 | P13: =O13/N13 -> 0.30495611 | Q13: =IF(P13<0.1,"X",IF(P13<0.25,"Y","Z")) -> Z | R13: Электроника-акс.
A14: Крем для лица 50 мл | B14: 95353.942 | C14: 72186.486 | D14: 90285.707 | E14: 103685.82 | F14: 91852.416 | G14: 102017.59 | H14: 59992.965 | I14: 54842.92 | J14: 93407.76 | K14: 109154.54 | L14: 76412.376 | M14: 124732.54 | N14: =AVERAGE(B14:M14) -> 89493.755 | O14: =STDEV(B14:M14) -> 20414.061 | P14: =O14/N14 -> 0.22810598 | Q14: =IF(P14<0.1,"X",IF(P14<0.25,"Y","Z")) -> Y | R14: Косметика и уход
A15: Ежедневник А5 датированный | B15: 45019.224 | C15: 32536.935 | D15: 36057.052 | E15: 34934.719 | F15: 47746.516 | G15: 45994.965 | H15: 54802.71 | I15: 158648.1 | J15: 111642.14 | K15: 50795.439 | L15: 43471.89 | M15: 88501.578 | N15: =AVERAGE(B15:M15) -> 62512.606 | O15: =STDEV(B15:M15) -> 38193.669 | P15: =O15/N15 -> 0.61097547 | Q15: =IF(P15<0.1,"X",IF(P15<0.25,"Y","Z")) -> Z | R15: Канцелярия
A16: Эспандер кистевой пара | B16: 80054.455 | C16: 63051.766 | D16: 56013.988 | E16: 62172.547 | F16: 47709.305 | G16: 48366.894 | H16: 49211.85 | I16: 47595.353 | J16: 38745.045 | K16: 47699.406 | L16: 26883.075 | M16: 24540.571 | N16: =AVERAGE(B16:M16) -> 49337.021 | O16: =STDEV(B16:M16) -> 15319.455 | P16: =O16/N16 -> 0.31050628 | Q16: =IF(P16<0.1,"X",IF(P16<0.25,"Y","Z")) -> Z | R16: Спорт
... A19: Набор маркеров 12 цветов | B19: 8731.9257 | C19: 7060.1911 | D19: 6370.7184 | E19: 5780.4587 | F19: 8806.7179 | G19: 11714.283 | H19: 10498.895 | I19: 27874.882 | J19: 29150.24 | K19: 11244.85 | L19: 6934.2282 | M19: 22801.813 | N19: =AVERAGE(B19:M19) -> 13080.767 | O19: =STDEV(B19:M19) -> 8490.7592 | P19: =O19/N19 -> 0.64910255 | Q19: =IF(P19<0.1,"X",IF(P19<0.25,"Y","Z")) -> Z | R19: Канцелярия
A21: Вывод и рекомендация
A22: 1. Топовые SKU класса A в основном попадают в X (стабильно) и Y (сезонно): можно планировать «под план», для Y учитывать сезонные коэффициенты.
A23: 2. Хвост ассортимента (мелкие SKU) — в основном Z. Это нормально: их продажи нерегулярны, закупаем под подтверждённый спрос или как long tail.
A24: 3. Категория «Канцелярия» — выраженный Y (август-сентябрь = школа, декабрь = подарки). Под этот пик резервируем рекламный бюджет за 4-6 недель.
A25: 4. Категория «Спорт» — паттерн «январь + весна», но топ-SKU (гантели, коврик) держатся стабильнее остальных за счёт корпоративных закупок.
A26: 5. Без ABC XYZ обманчив: стабильный SKU может приносить 0.5% выручки. Смотрим в паре — лист 05.

Sheet 05_ABC_XYZ_матрица
A1: 05. Стратегическая матрица ABC × XYZ
A2: Метод: пересечение классов ABC и XYZ → 9 ячеек × готовая стратегия. Используем для квартальной ассортиментной планёрки.
A4: Назначение стратегии каждому SKU | F4: Справочник стратегий
A5: SKU | B5: Класс ABC | C5: Класс XYZ | D5: Код | E5: Стратегия | F5: Код | G5: Стратегия
A6: Подушка ортопедическая 50×70 | B6: =VLOOKUP(A6,03_ABC_анализ!$B$5:$G$19,6,FALSE()) -> A | C6: =VLOOKUP(A6,04_XYZ_анализ!$A$5:$Q$19,17,FALSE()) -> Y | D6: =B6&C6 -> AY | E6: =VLOOKUP(D6,$F$6:$G$14,2,FALSE()) -> Прогноз с сезонностью. Промо-бюджет под пик. Контракты «по графику закупок». | F6: AX | G6: Защищать. Эксклюзивный сервис, страховой запас, прайс-стабильность.
A7: Набор постельного белья евро | B7: =VLOOKUP(A7,03_ABC_анализ!$B$5:$G$19,6,FALSE()) -> A | C7: =VLOOKUP(A7,04_XYZ_анализ!$A$5:$Q$19,17,FALSE()) -> Y | D7: =B7&C7 -> AY | E7: =VLOOKUP(D7,$F$6:$G$14,2,FALSE()) -> Прогноз с сезонностью. Промо-бюджет под пик. Контракты «по графику закупок». | F7: AY | G7: Прогноз с сезонностью. Промо-бюджет под пик. Контракты «по графику закупок».
A8: Гантели разборные 10 кг | B8: =VLOOKUP(A8,03_ABC_анализ!$B$5:$G$19,6,FALSE()) -> A | C8: =VLOOKUP(A8,04_XYZ_анализ!$A$5:$Q$19,17,FALSE()) -> Y | D8: =B8&C8 -> AY | E8: =VLOOKUP(D8,$F$6:$G$14,2,FALSE()) -> Прогноз с сезонностью. Промо-бюджет под пик. Контракты «по графику закупок». | F8: AZ | G8: Гибкое производство, work-on-demand, риск-надбавка, искать причины волатильности.
A9: Кофеварка капельная KS-200 | B9: =VLOOKUP(A9,03_ABC_анализ!$B$5:$G$19,6,FALSE()) -> A | C9: =VLOOKUP(A9,04_XYZ_анализ!$A$5:$Q$19,17,FALSE()) -> Y | D9: =B9&C9 -> AY | E9: =VLOOKUP(D9,$F$6:$G$14,2,FALSE()) -> Прогноз с сезонностью. Промо-бюджет под пик. Контракты «по графику закупок». | F9: BX | G9: Стандартный сервис, кросс-продажи в А-класс.
A10: Шампунь увлажняющий 400 мл | B10: =VLOOKUP(A10,03_ABC_анализ!$B$5:$G$19,6,FALSE()) -> A | C10: =VLOOKUP(A10,04_XYZ_анализ!$A$5:$Q$19,17,FALSE()) -> Y | D10: =B10&C10 -> AY | E10: =VLOOKUP(D10,$F$6:$G$14,2,FALSE()) -> Прогноз с сезонностью. Промо-бюджет под пик. Контракты «по графику закупок». | F10: BY | G10: Промо в низкий сезон, бандлы с А-классом.
A11: Наушники TWS базовые | B11: =VLOOKUP(A11,03_ABC_анализ!$B$5:$G$19,6,FALSE()) -> A | C11: =VLOOKUP(A11,04_XYZ_анализ!$A$5:$Q$19,17,FALSE()) -> Y | D11: =B11&C11 -> AY | E11: =VLOOKUP(D11,$F$6:$G$14,2,FALSE()) -> Прогноз с сезонностью. Промо-бюджет под пик. Контракты «по графику закупок». | F11: BZ | G11: Ручной контроль, оптимизация пакетирования, переговоры о предзаказах.
A12: Коврик для йоги 6 мм | B12: =VLOOKUP(A12,03_ABC_анализ!$B$5:$G$19,6,FALSE()) -> A | C12: =VLOOKUP(A12,04_XYZ_анализ!$A$5:$Q$19,17,FALSE()) -> Y | D12: =B12&C12 -> AY | E12: =VLOOKUP(D12,$F$6:$G$14,2,FALSE()) -> Прогноз с сезонностью. Промо-бюджет под пик. Контракты «по графику закупок». | F12: CX | G12: Long tail / сервис лояльных. Без активных инвестиций.
A13: Кабель USB-C → USB-C, 1 м | B13: =VLOOKUP(A13,03_ABC_анализ!$B$5:$G$19,6,FALSE()) -> B | C13: =VLOOKUP(A13,04_XYZ_анализ!$A$5:$Q$19,17,FALSE()) -> Z | D13: =B13&C13 -> BZ | E13: =VLOOKUP(D13,$F$6:$G$14,2,FALSE()) -> Ручной контроль, оптимизация пакетирования, переговоры о предзаказах. | F13: CY | G13: Минимальные обязательства, без склада.
A14: Колонка Bluetooth портативная | B14: =VLOOKUP(A14,03_ABC_анализ!$B$5:$G$19,6,FALSE()) -> B | C14: =VLOOKUP(A14,04_XYZ_анализ!$A$5:$Q$19,17,FALSE()) -> Z | D14: =B14&C14 -> BZ | E14: =VLOOKUP(D14,$F$6:$G$14,2,FALSE()) -> Ручной контроль, оптимизация пакетирования, переговоры о предзаказах. | F14: CZ | G14: Кандидаты на вывод из ассортимента.
A15: Крем для лица 50 мл | B15: =VLOOKUP(A15,03_ABC_анализ!$B$5:$G$19,6,FALSE()) -> B | C15: =VLOOKUP(A15,04_XYZ_анализ!$A$5:$Q$19,17,FALSE()) -> Y | D15: =B15&C15 -> BY | E15: =VLOOKUP(D15,$F$6:$G$14,2,FALSE()) -> Промо в низкий сезон, бандлы с А-классом.
A16: Ежедневник А5 датированный | B16: =VLOOKUP(A16,03_ABC_анализ!$B$5:$G$19,6,FALSE()) -> C | C16: =VLOOKUP(A16,04_XYZ_анализ!$A$5:$Q$19,17,FALSE()) -> Z | D16: =B16&C16 -> CZ | E16: =VLOOKUP(D16,$F$6:$G$14,2,FALSE()) -> Кандидаты на вывод из ассортимента.
A17: Эспандер кистевой пара | B17: =VLOOKUP(A17,03_ABC_анализ!$B$5:$G$19,6,FALSE()) -> C | C17: =VLOOKUP(A17,04_XYZ_анализ!$A$5:$Q$19,17,FALSE()) -> Z | D17: =B17&C17 -> CZ | E17: =VLOOKUP(D17,$F$6:$G$14,2,FALSE()) -> Кандидаты на вывод из ассортимента.
A18: Парфюм женский 50 мл | B18: =VLOOKUP(A18,03_ABC_анализ!$B$5:$G$19,6,FALSE()) -> C | C18: =VLOOKUP(A18,04_XYZ_анализ!$A$5:$Q$19,17,FALSE()) -> Y | D18: =B18&C18 -> CY | E18: =VLOOKUP(D18,$F$6:$G$14,2,FALSE()) -> Минимальные обязательства, без склада.
A19: Маска тканевая (упаковка) | B19: =VLOOKUP(A19,03_ABC_анализ!$B$5:$G$19,6,FALSE()) -> C | C19: =VLOOKUP(A19,04_XYZ_анализ!$A$5:$Q$19,17,FALSE()) -> Z | D19: =B19&C19 -> CZ | E19: =VLOOKUP(D19,$F$6:$G$14,2,FALSE()) -> Кандидаты на вывод из ассортимента.
A20: Набор маркеров 12 цветов | B20: =VLOOKUP(A20,03_ABC_анализ!$B$5:$G$19,6,FALSE()) -> C | C20: =VLOOKUP(A20,04_XYZ_анализ!$A$5:$Q$19,17,FALSE()) -> Z | D20: =B20&C20 -> CZ | E20: =VLOOKUP(D20,$F$6:$G$14,2,FALSE()) -> Кандидаты на вывод из ассортимента.
A23: Вывод и рекомендация
A24: 1. SKU AX и AY (топ-выручка + предсказуемые) — фундамент бизнеса. Защищаем контрактами с поставщиком, держим страховой запас, не «выжигаем» маржу промо.
A25: 2. AZ (топ-выручка + волатильно) — самая опасная клетка. Нужно понять, почему скачет: реклама нерегулярная? сезонность не учли? конкурент делает атаки?
A26: 3. CZ — приоритет для ассортиментной ревизии. Если SKU не «эмоциональная» позиция (например, не закрывает базовую потребность лояльных) — выводим.
A27: 4. Эта матрица — повестка квартальной ассортиментной планёрки. Каждые 3 мес. пересобираем и обсуждаем с руководителем.

Sheet 06_Юнит_экономика
A1: 06. Юнит-экономика по SKU
A2: Цена → COGS → валовая маржа → контрибуционная маржа → прибыль/год. Прямые ОПЕР — комиссия маркетплейса + логистика + упаковка ≈ 22% от цены.
A4: SKU | B4: Цена ₽ | C4: COGS ₽ | D4: Маржа ₽ | E4: Маржа % | F4: Объём/год (шт) | G4: Выручка/год ₽ | H4: Прибыль/год ₽ | I4: Контриб. на ед. ₽
A5: Подушка ортопедическая 50×70 | B5: 1490 | C5: 680 | D5: =B5-C5 -> 810 | E5: =D5/B5 -> 0.54362416 | F5: 3258 | G5: =B5*F5 -> 4854420 | H5: =D5*F5 -> 2638980 | I5: =D5-B5*0.22 -> 482.2
A6: Набор постельного белья евро | B6: 2890 | C6: 1420 | D6: =B6-C6 -> 1470 | E6: =D6/B6 -> 0.50865052 | F6: 1356 | G6: =B6*F6 -> 3918840 | H6: =D6*F6 -> 1993320 | I6: =D6-B6*0.22 -> 834.2
A7: Гантели разборные 10 кг | B7: 3990 | C7: 2150 | D7: =B7-C7 -> 1840 | E7: =D7/B7 -> 0.46115288 | F7: 855 | G7: =B7*F7 -> 3411450 | H7: =D7*F7 -> 1573200 | I7: =D7-B7*0.22 -> 962.2
A8: Кофеварка капельная KS-200 | B8: 4490 | C8: 2680 | D8: =B8-C8 -> 1810 | E8: =D8/B8 -> 0.40311804 | F8: 664 | G8: =B8*F8 -> 2981360 | H8: =D8*F8 -> 1201840 | I8: =D8-B8*0.22 -> 822.2
A9: Шампунь увлажняющий 400 мл | B9: 590 | C9: 220 | D9: =B9-C9 -> 370 | E9: =D9/B9 -> 0.62711864 | F9: 4305 | G9: =B9*F9 -> 2539950 | H9: =D9*F9 -> 1592850 | I9: =D9-B9*0.22 -> 240.2
A10: Наушники TWS базовые | B10: 1890 | C10: 890 | D10: =B10-C10 -> 1000 | E10: =D10/B10 -> 0.52910053 | F10: 1122 | G10: =B10*F10 -> 2120580 | H10: =D10*F10 -> 1122000 | I10: =D10-B10*0.22 -> 584.2
A11: ИТОГО | G11: =SUM(G5:G10) -> 19826600 | H11: =SUM(H5:H10) -> 10122190
A13: Точка безубыточности (BEP) бизнес-юнита
A14: Постоянные затраты в год (ФОТ, аренда, маркетинг постоянный, амортизация) | B14: 4200000
A15: Средняя контрибуция на единицу (по топ-6 SKU) | B15: =AVERAGE(I5:I10) -> 654.2
A16: BEP (ед./год) | B16: =B14/B15 -> 6420.055
A17: Текущий объём год по топ-6 | B17: =SUM(F5:F10) -> 11560
A18: Запас прочности | B18: =(B17-B16)/B17 -> 0.44463192
A20: Вывод и рекомендация
A21: 1. Самые маржинальные в % — шампунь и подушка (50%+ валовая, ~30% контрибуционная). Самый маржинальный в ₽ — кофеварка (1810 ₽ валовой на ед., 813 ₽ контрибуции).
A22: 2. Гантели и наушники — на грани: после комиссии маркетплейса 22% контрибуция падает до ~10–15%. Это «оборотные» SKU: важны не для прибыли, а для трафика на карточку магазина.
A23: 3. BEP бизнес-юнита: ~6 200 ед./год. Текущий объём ~12 тыс. → запас прочности ~50%. Здоровый показатель.
A24: 4. Если хотим снизить цену гантелей на 10% (промо), маржа упадёт с 46% до 39%, контрибуция уйдёт в ноль — нельзя без компенсации объёмом ×1.5.

Sheet 07_ROI_новый_продукт
A1: 07. ROI / payback запуска новой категории «Smart-home аксессуары»
A2: 5-летняя финансовая модель. Жёлтые ячейки = допущения. Жмёшь жёлтые — обновляются NPV/IRR/Payback и таблица чувствительности.
A4: Допущения (вводятся вручную)
A5: Инвестиция (CAPEX), ₽ | B5: 4500000
A6: Цена за единицу, ₽ | B6: 2290
A7: COGS на единицу, ₽ | B7: 1350
A8: Объём год 1 (шт) | B8: 3500
A9: Темп роста объёма год к году | B9: 0.25
A10: Постоянные затраты в год, ₽ | B10: 1080000
A11: Ставка дисконта (WACC) | B11: 0.2
A12: Горизонт (лет) | B12: 5
A14: Прогноз денежного потока
B15: Год 0 | C15: Год 1 | D15: Год 2 | E15: Год 3 | F15: Год 4 | G15: Год 5
A16: Объём (шт) | B16: 0 | C16: =$B$8 -> 3500 | D16: =C16*(1+$B$9) -> 4375 | E16: =D16*(1+$B$9) -> 5468.75 | F16: =E16*(1+$B$9) -> 6835.9375 | G16: =F16*(1+$B$9) -> 8544.9219
A17: Выручка, ₽ | B17: 0 | C17: =C16*$B$6 -> 8015000 | D17: =D16*$B$6 -> 10018750 | E17: =E16*$B$6 -> 12523438 | F17: =F16*$B$6 -> 15654297 | G17: =G16*$B$6 -> 19567871
A18: COGS, ₽ | B18: 0 | C18: =-C16*$B$7 -> -4725000 | D18: =-D16*$B$7 -> -5906250 | E18: =-E16*$B$7 -> -7382812.5 | F18: =-F16*$B$7 -> -9228515.6 | G18: =-G16*$B$7 -> -11535645
A19: Постоянные, ₽ | B19: 0 | C19: =-$B$10 -> -1080000 | D19: =-$B$10 -> -1080000 | E19: =-$B$10 -> -1080000 | F19: =-$B$10 -> -1080000 | G19: =-$B$10 -> -1080000
A20: Операционный CF, ₽ | B20: 0 | C20: =C17+C18+C19 -> 2210000 | D20: =D17+D18+D19 -> 3032500 | E20: =E17+E18+E19 -> 4060625 | F20: =F17+F18+F19 -> 5345781.2 | G20: =G17+G18+G19 -> 6952226.6
A21: CAPEX, ₽ | B21: =-$B$5 -> -4500000 | C21: =0 -> 0 | D21: =0 -> 0 | E21: =0 -> 0 | F21: =0 -> 0 | G21: =0 -> 0
A22: Чистый CF, ₽ | B22: =B20+B21 -> -4500000 | C22: =C20+C21 -> 2210000 | D22: =D20+D21 -> 3032500 | E22: =E20+E21 -> 4060625 | F22: =F20+F21 -> 5345781.2 | G22: =G20+G21 -> 6952226.6
A23: Накопит. CF, ₽ | B23: =B22 -> -4500000 | C23: =B23+C22 -> -2290000 | D23: =C23+D22 -> 742500 | E23: =D23+E22 -> 4803125 | F23: =E23+F22 -> 10148906 | G23: =F23+G22 -> 17101133
A25: Финансовые метрики
A26: NPV (чистая приведённая стоимость), ₽ | B26: =B22+NPV($B$11,C22:G22) -> 7169431.6
A27: IRR (внутренняя норма доходности) | B27: =IRR(B22:G22) -> 0.6707363
A28: Payback (период окупаемости) | B28: =IFERROR(MATCH(TRUE(),C23:G23>=0,0),"больше горизонта") -> 2
A29: ROI 5 лет | B29: =SUM(C22:G22)/(-B22) -> 4.8002517
A31: Таблица чувствительности NPV: цена × объём год 1
A32: Цена ₽ ↓ / Объём год 1 → | B32: 2500 | C32: 3000 | D32: 3500 | E32: 4000 | F32: 4500
A33: 2090 | B33: =-$B$5+((2500*(1+$B$9)^0)*(2090-$B$7)-$B$10)/(1+$B$11)^1+((2500*(1+$B$9)^1)*(2090-$B$7)-$B$10)/(1+$B$11)^2+((2500*(1+$B$9)^2)*(2090-$B$7)-$B$10)/(1+$B$11)^3+((2500*(1+$B$9)^3)*(2090-$B$7)-$B$10)/(1+$B$11)^4+((2500*(1+$B$9)^4)*(2090-$B$7)-$B$10)/(1+$B$11)^5 -> 648160.63 | C33: =-$B$5+((3000*(1+$B$9)^0)*(2090-$B$7)-$B$10)/(1+$B$11)^1+((3000*(1+$B$9)^1)*(2090-$B$7)-$B$10)/(1+$B$11)^2+((3000*(1+$B$9)^2)*(2090-$B$7)-$B$10)/(1+$B$11)^3+((3000*(1+$B$9)^3)*(2090-$B$7)-$B$10)/(1+$B$11)^4+((3000*(1+$B$9)^4)*(2090-$B$7)-$B$10)/(1+$B$11)^5 -> 2323765 | D33: =-$B$5+((3500*(1+$B$9)^0)*(2090-$B$7)-$B$10)/(1+$B$11)^1+((3500*(1+$B$9)^1)*(2090-$B$7)-$B$10)/(1+$B$11)^2+((3500*(1+$B$9)^2)*(2090-$B$7)-$B$10)/(1+$B$11)^3+((3500*(1+$B$9)^3)*(2090-$B$7)-$B$10)/(1+$B$11)^4+((3500*(1+$B$9)^4)*(2090-$B$7)-$B$10)/(1+$B$11)^5 -> 3999369.3 | E33: =-$B$5+((4000*(1+$B$9)^0)*(2090-$B$7)-$B$10)/(1+$B$11)^1+((4000*(1+$B$9)^1)*(2090-$B$7)-$B$10)/(1+$B$11)^2+((4000*(1+$B$9)^2)*(2090-$B$7)-$B$10)/(1+$B$11)^3+((4000*(1+$B$9)^3)*(2090-$B$7)-$B$10)/(1+$B$11)^4+((4000*(1+$B$9)^4)*(2090-$B$7)-$B$10)/(1+$B$11)^5 -> 5674973.7 | F33: =-$B$5+((4500*(1+$B$9)^0)*(2090-$B$7)-$B$10)/(1+$B$11)^1+((4500*(1+$B$9)^1)*(2090-$B$7)-$B$10)/(1+$B$11)^2+((4500*(1+$B$9)^2)*(2090-$B$7)-$B$10)/(1+$B$11)^3+((4500*(1+$B$9)^3)*(2090-$B$7)-$B$10)/(1+$B$11)^4+((4500*(1+$B$9)^4)*(2090-$B$7)-$B$10)/(1+$B$11)^5 -> 7350578
A34: 2190 | B34: =-$B$5+((2500*(1+$B$9)^0)*(2190-$B$7)-$B$10)/(1+$B$11)^1+((2500*(1+$B$9)^1)*(2190-$B$7)-$B$10)/(1+$B$11)^2+((2500*(1+$B$9)^2)*(2190-$B$7)-$B$10)/(1+$B$11)^3+((2500*(1+$B$9)^3)*(2190-$B$7)-$B$10)/(1+$B$11)^4+((2500*(1+$B$9)^4)*(2190-$B$7)-$B$10)/(1+$B$11)^5 -> 1780325.7 | C34: =-$B$5+((3000*(1+$B$9)^0)*(2190-$B$7)-$B$10)/(1+$B$11)^1+((3000*(1+$B$9)^1)*(2190-$B$7)-$B$10)/(1+$B$11)^2+((3000*(1+$B$9)^2)*(2190-$B$7)-$B$10)/(1+$B$11)^3+((3000*(1+$B$9)^3)*(2190-$B$7)-$B$10)/(1+$B$11)^4+((3000*(1+$B$9)^4)*(2190-$B$7)-$B$10)/(1+$B$11)^5 -> 3682363.1 | D34: =-$B$5+((3500*(1+$B$9)^0)*(2190-$B$7)-$B$10)/(1+$B$11)^1+((3500*(1+$B$9)^1)*(2190-$B$7)-$B$10)/(1+$B$11)^2+((3500*(1+$B$9)^2)*(2190-$B$7)-$B$10)/(1+$B$11)^3+((3500*(1+$B$9)^3)*(2190-$B$7)-$B$10)/(1+$B$11)^4+((3500*(1+$B$9)^4)*(2190-$B$7)-$B$10)/(1+$B$11)^5 -> 5584400.5 | E34: =-$B$5+((4000*(1+$B$9)^0)*(2190-$B$7)-$B$10)/(1+$B$11)^1+((4000*(1+$B$9)^1)*(2190-$B$7)-$B$10)/(1+$B$11)^2+((4000*(1+$B$9)^2)*(2190-$B$7)-$B$10)/(1+$B$11)^3+((4000*(1+$B$9)^3)*(2190-$B$7)-$B$10)/(1+$B$11)^4+((4000*(1+$B$9)^4)*(2190-$B$7)-$B$10)/(1+$B$11)^5 -> 7486437.8 | F34: =-$B$5+((4500*(1+$B$9)^0)*(2190-$B$7)-$B$10)/(1+$B$11)^1+((4500*(1+$B$9)^1)*(2190-$B$7)-$B$10)/(1+$B$11)^2+((4500*(1+$B$9)^2)*(2190-$B$7)-$B$10)/(1+$B$11)^3+((4500*(1+$B$9)^3)*(2190-$B$7)-$B$10)/(1+$B$11)^4+((4500*(1+$B$9)^4)*(2190-$B$7)-$B$10)/(1+$B$11)^5 -> 9388475.2
A35: 2290 | B35: =-$B$5+((2500*(1+$B$9)^0)*(2290-$B$7)-$B$10)/(1+$B$11)^1+((2500*(1+$B$9)^1)*(2290-$B$7)-$B$10)/(1+$B$11)^2+((2500*(1+$B$9)^2)*(2290-$B$7)-$B$10)/(1+$B$11)^3+((2500*(1+$B$9)^3)*(2290-$B$7)-$B$10)/(1+$B$11)^4+((2500*(1+$B$9)^4)*(2290-$B$7)-$B$10)/(1+$B$11)^5 -> 2912490.8 | C35: =-$B$5+((3000*(1+$B$9)^0)*(2290-$B$7)-$B$10)/(1+$B$11)^1+((3000*(1+$B$9)^1)*(2290-$B$7)-$B$10)/(1+$B$11)^2+((3000*(1+$B$9)^2)*(2290-$B$7)-$B$10)/(1+$B$11)^3+((3000*(1+$B$9)^3)*(2290-$B$7)-$B$10)/(1+$B$11)^4+((3000*(1+$B$9)^4)*(2290-$B$7)-$B$10)/(1+$B$11)^5 -> 5040961.2 | D35: =-$B$5+((3500*(1+$B$9)^0)*(2290-$B$7)-$B$10)/(1+$B$11)^1+((3500*(1+$B$9)^1)*(2290-$B$7)-$B$10)/(1+$B$11)^2+((3500*(1+$B$9)^2)*(2290-$B$7)-$B$10)/(1+$B$11)^3+((3500*(1+$B$9)^3)*(2290-$B$7)-$B$10)/(1+$B$11)^4+((3500*(1+$B$9)^4)*(2290-$B$7)-$B$10)/(1+$B$11)^5 -> 7169431.6 | E35: =-$B$5+((4000*(1+$B$9)^0)*(2290-$B$7)-$B$10)/(1+$B$11)^1+((4000*(1+$B$9)^1)*(2290-$B$7)-$B$10)/(1+$B$11)^2+((4000*(1+$B$9)^2)*(2290-$B$7)-$B$10)/(1+$B$11)^3+((4000*(1+$B$9)^3)*(2290-$B$7)-$B$10)/(1+$B$11)^4+((4000*(1+$B$9)^4)*(2290-$B$7)-$B$10)/(1+$B$11)^5 -> 9297902 | F35: =-$B$5+((4500*(1+$B$9)^0)*(2290-$B$7)-$B$10)/(1+$B$11)^1+((4500*(1+$B$9)^1)*(2290-$B$7)-$B$10)/(1+$B$11)^2+((4500*(1+$B$9)^2)*(2290-$B$7)-$B$10)/(1+$B$11)^3+((4500*(1+$B$9)^3)*(2290-$B$7)-$B$10)/(1+$B$11)^4+((4500*(1+$B$9)^4)*(2290-$B$7)-$B$10)/(1+$B$11)^5 -> 11426372
A36: 2390 | B36: =-$B$5+((2500*(1+$B$9)^0)*(2390-$B$7)-$B$10)/(1+$B$11)^1+((2500*(1+$B$9)^1)*(2390-$B$7)-$B$10)/(1+$B$11)^2+((2500*(1+$B$9)^2)*(2390-$B$7)-$B$10)/(1+$B$11)^3+((2500*(1+$B$9)^3)*(2390-$B$7)-$B$10)/(1+$B$11)^4+((2500*(1+$B$9)^4)*(2390-$B$7)-$B$10)/(1+$B$11)^5 -> 4044655.9 | C36: =-$B$5+((3000*(1+$B$9)^0)*(2390-$B$7)-$B$10)/(1+$B$11)^1+((3000*(1+$B$9)^1)*(2390-$B$7)-$B$10)/(1+$B$11)^2+((3000*(1+$B$9)^2)*(2390-$B$7)-$B$10)/(1+$B$11)^3+((3000*(1+$B$9)^3)*(2390-$B$7)-$B$10)/(1+$B$11)^4+((3000*(1+$B$9)^4)*(2390-$B$7)-$B$10)/(1+$B$11)^5 -> 6399559.3 | D36: =-$B$5+((3500*(1+$B$9)^0)*(2390-$B$7)-$B$10)/(1+$B$11)^1+((3500*(1+$B$9)^1)*(2390-$B$7)-$B$10)/(1+$B$11)^2+((3500*(1+$B$9)^2)*(2390-$B$7)-$B$10)/(1+$B$11)^3+((3500*(1+$B$9)^3)*(2390-$B$7)-$B$10)/(1+$B$11)^4+((3500*(1+$B$9)^4)*(2390-$B$7)-$B$10)/(1+$B$11)^5 -> 8754462.7 | E36: =-$B$5+((4000*(1+$B$9)^0)*(2390-$B$7)-$B$10)/(1+$B$11)^1+((4000*(1+$B$9)^1)*(2390-$B$7)-$B$10)/(1+$B$11)^2+((4000*(1+$B$9)^2)*(2390-$B$7)-$B$10)/(1+$B$11)^3+((4000*(1+$B$9)^3)*(2390-$B$7)-$B$10)/(1+$B$11)^4+((4000*(1+$B$9)^4)*(2390-$B$7)-$B$10)/(1+$B$11)^5 -> 11109366 | F36: =-$B$5+((4500*(1+$B$9)^0)*(2390-$B$7)-$B$10)/(1+$B$11)^1+((4500*(1+$B$9)^1)*(2390-$B$7)-$B$10)/(1+$B$11)^2+((4500*(1+$B$9)^2)*(2390-$B$7)-$B$10)/(1+$B$11)^3+((4500*(1+$B$9)^3)*(2390-$B$7)-$B$10)/(1+$B$11)^4+((4500*(1+$B$9)^4)*(2390-$B$7)-$B$10)/(1+$B$11)^5 -> 13464270
A37: 2490 | B37: =-$B$5+((2500*(1+$B$9)^0)*(2490-$B$7)-$B$10)/(1+$B$11)^1+((2500*(1+$B$9)^1)*(2490-$B$7)-$B$10)/(1+$B$11)^2+((2500*(1+$B$9)^2)*(2490-$B$7)-$B$10)/(1+$B$11)^3+((2500*(1+$B$9)^3)*(2490-$B$7)-$B$10)/(1+$B$11)^4+((2500*(1+$B$9)^4)*(2490-$B$7)-$B$10)/(1+$B$11)^5 -> 5176821 | C37: =-$B$5+((3000*(1+$B$9)^0)*(2490-$B$7)-$B$10)/(1+$B$11)^1+((3000*(1+$B$9)^1)*(2490-$B$7)-$B$10)/(1+$B$11)^2+((3000*(1+$B$9)^2)*(2490-$B$7)-$B$10)/(1+$B$11)^3+((3000*(1+$B$9)^3)*(2490-$B$7)-$B$10)/(1+$B$11)^4+((3000*(1+$B$9)^4)*(2490-$B$7)-$B$10)/(1+$B$11)^5 -> 7758157.5 | D37: =-$B$5+((3500*(1+$B$9)^0)*(2490-$B$7)-$B$10)/(1+$B$11)^1+((3500*(1+$B$9)^1)*(2490-$B$7)-$B$10)/(1+$B$11)^2+((3500*(1+$B$9)^2)*(2490-$B$7)-$B$10)/(1+$B$11)^3+((3500*(1+$B$9)^3)*(2490-$B$7)-$B$10)/(1+$B$11)^4+((3500*(1+$B$9)^4)*(2490-$B$7)-$B$10)/(1+$B$11)^5 -> 10339494 | E37: =-$B$5+((4000*(1+$B$9)^0)*(2490-$B$7)-$B$10)/(1+$B$11)^1+((4000*(1+$B$9)^1)*(2490-$B$7)-$B$10)/(1+$B$11)^2+((4000*(1+$B$9)^2)*(2490-$B$7)-$B$10)/(1+$B$11)^3+((4000*(1+$B$9)^3)*(2490-$B$7)-$B$10)/(1+$B$11)^4+((4000*(1+$B$9)^4)*(2490-$B$7)-$B$10)/(1+$B$11)^5 -> 12920830 | F37: =-$B$5+((4500*(1+$B$9)^0)*(2490-$B$7)-$B$10)/(1+$B$11)^1+((4500*(1+$B$9)^1)*(2490-$B$7)-$B$10)/(1+$B$11)^2+((4500*(1+$B$9)^2)*(2490-$B$7)-$B$10)/(1+$B$11)^3+((4500*(1+$B$9)^3)*(2490-$B$7)-$B$10)/(1+$B$11)^4+((4500*(1+$B$9)^4)*(2490-$B$7)-$B$10)/(1+$B$11)^5 -> 15502167
A39: Вывод и рекомендация
A40: 1. Базовый сценарий (цена 2 290, объём 3 500): NPV положительный, IRR > WACC. Запуск рентабелен.
A41: 2. Чувствительность: при просадке цены до 2 090 ₽ и объёма до 2 500 шт NPV уходит в минус. Это «дно» переговоров с поставщиком/контракта с маркетплейсом.
A42: 3. Перед запуском нужно: подтвердить контракт с поставщиком на ≥ 3 000 шт год 1 на оптовой цене ≤ 1 120 ₽, иначе модель не сходится.
A43: 4. Решение: GO с условиями — фиксируем объём, контролируем COGS, в первый месяц мониторим продажи неделя-к-неделе. Если объём < плана на 30% за 30 дней — пересматриваем модель.

Sheet 08_Сезонность
A1: 08. Сезонность по категориям и прогноз на следующий период
A2: Метод: помесячные продажи за 12 мес. → сезонный коэффициент = месяц / среднее. Сумма коэффициентов ≈ 12. Прогноз = годовой_план / 12 × коэф.
A4: Категория | B4: Янв | C4: Фев | D4: Мар | E4: Апр | F4: Май | G4: Июн | H4: Июл | I4: Авг | J4: Сен | K4: Окт | L4: Ноя | M4: Дек | N4: Среднее
A5: Товары для дома | B5: 682539 | C5: 658345 | D5: 781231 | E5: 761594 | F5: 774960 | G5: 713401 | H5: 703868 | I5: 669781 | J5: 769551 | K5: 831689 | L5: 1222334 | M5: 1200789 | N5: =AVERAGE(B5:M5) -> 814173.5
A6: Косметика и уход | B6: 329524 | C6: 359733 | D6: 445863 | E6: 341340 | F6: 345887 | G6: 313268 | H6: 307150 | I6: 282911 | J6: 309777 | K6: 334208 | L6: 361682 | M6: 631729 | N6: =AVERAGE(B6:M6) -> 363589.33
A7: Спорт | B7: 657498 | C7: 609472 | D7: 582035 | E7: 535688 | F7: 511135 | G7: 463866 | H7: 489889 | I7: 413897 | J7: 374331 | K7: 396307 | L7: 393064 | M7: 291153 | N7: =AVERAGE(B7:M7) -> 476527.92
A8: Электроника-акс. | B8: 403753 | C8: 371779 | D8: 398409 | E8: 393537 | F8: 400391 | G8: 390210 | H8: 364773 | I8: 342691 | J8: 399872 | K8: 419252 | L8: 699199 | M8: 460426 | N8: =AVERAGE(B8:M8) -> 420357.67
A9: Канцелярия | B9: 47700 | C9: 48447 | D9: 48263 | E9: 48114 | F9: 50232 | G9: 54210 | H9: 78982 | I9: 155318 | J9: 167101 | K9: 75012 | L9: 49383 | M9: 121000 | N9: =AVERAGE(B9:M9) -> 78646.833
A11: Сезонные коэффициенты (месяц / среднее)
A12: Категория | B12: Янв | C12: Фев | D12: Мар | E12: Апр | F12: Май | G12: Июн | H12: Июл | I12: Авг | J12: Сен | K12: Окт | L12: Ноя | M12: Дек | N12: Среднее
A13: Товары для дома | B13: =B5/N5 -> 0.83832132 | C13: =C5/N5 -> 0.80860529 | D13: =D5/N5 -> 0.95953872 | E13: =E5/N5 -> 0.93541978 | F13: =F5/N5 -> 0.95183643 | G13: =G5/N5 -> 0.87622724 | H13: =H5/N5 -> 0.86451843 | I13: =I5/N5 -> 0.82265144 | J13: =J5/N5 -> 0.94519289 | K13: =K5/N5 -> 1.0215132 | L13: =L5/N5 -> 1.5013188 | M13: =M5/N5 -> 1.4748564 | N13: =AVERAGE(B13:M13) -> 1
A14: Косметика и уход | B14: =B6/N6 -> 0.90630822 | C14: =C6/N6 -> 0.98939371 | D14: =D6/N6 -> 1.2262818 | E14: =E6/N6 -> 0.93880642 | F14: =F6/N6 -> 0.95131229 | G14: =G6/N6 -> 0.86159843 | H14: =H6/N6 -> 0.84477176 | I14: =I6/N6 -> 0.77810589 | J14: =J6/N6 -> 0.85199694 | K14: =K6/N6 -> 0.91919088 | L14: =L6/N6 -> 0.99475415 | M14: =M6/N6 -> 1.7374795 | N14: =AVERAGE(B14:M14) -> 1
A15: Спорт | B15: =B7/N7 -> 1.3797681 | C15: =C7/N7 -> 1.2789849 | D15: =D7/N7 -> 1.221408 | E15: =E7/N7 -> 1.1241482 | F15: =F7/N7 -> 1.0726234 | G15: =G7/N7 -> 0.9734288 | H15: =H7/N7 -> 1.0280384 | I15: =I7/N7 -> 0.86856821 | J15: =J7/N7 -> 0.78553845 | K15: =K7/N7 -> 0.83165537 | L15: =L7/N7 -> 0.82484989 | M15: =M7/N7 -> 0.61098834 | N15: =AVERAGE(B15:M15) -> 1
A16: Электроника-акс. | B16: =B8/N8 -> 0.96049872 | C16: =C8/N8 -> 0.88443492 | D16: =D8/N8 -> 0.94778573 | E16: =E8/N8 -> 0.9361956 | F16: =F8/N8 -> 0.95250077 | G16: =G8/N8 -> 0.92828092 | H16: =H8/N8 -> 0.86776816 | I16: =I8/N8 -> 0.81523671 | J16: =J8/N8 -> 0.9512661 | K16: =K8/N8 -> 0.9973697 | L16: =L8/N8 -> 1.663343 | M16: =M8/N8 -> 1.0953196 | N16: =AVERAGE(B16:M16) -> 1
A17: Канцелярия | B17: =B9/N9 -> 0.60650884 | C17: =C9/N9 -> 0.616007 | D17: =D9/N9 -> 0.61366743 | E17: =E9/N9 -> 0.61177288 | F17: =F9/N9 -> 0.6387034 | G17: =G9/N9 -> 0.68928395 | H17: =H9/N9 -> 1.0042617 | I17: =I9/N9 -> 1.9748793 | J17: =J9/N9 -> 2.1247009 | K17: =K9/N9 -> 0.95378284 | L17: =L9/N9 -> 0.62790831 | M17: =M9/N9 -> 1.5385235 | N17: =AVERAGE(B17:M17) -> 1
A20: Прогноз на следующий год (при росте +20% к текущему)
A21: Категория | B21: Янв | C21: Фев | D21: Мар | E21: Апр | F21: Май | G21: Июн | H21: Июл | I21: Авг | J21: Сен | K21: Окт | L21: Ноя | M21: Дек | N21: Среднее
A22: Товары для дома | B22: =$N$22/12*B13 -> 817363.28 | C22: =$N$22/12*C13 -> 788390.16 | D22: =$N$22/12*D13 -> 935550.25 | E22: =$N$22/12*E13 -> 912034.29 | F22: =$N$22/12*F13 -> 928040.52 | G22: =$N$22/12*G13 -> 854321.56 | H22: =$N$22/12*H13 -> 842905.47 | I22: =$N$22/12*I13 -> 802085.15 | ... M22: =$N$22/12*M13 -> 1437985 | N22: =11700000 -> 11700000
A23: Косметика и уход | B23: =$N$23/12*B14 -> 394244.07 | C23: =$N$23/12*C14 -> 430386.26 | D23: =$N$23/12*D14 -> 533432.6 | E23: =$N$23/12*E14 -> 408380.79 | F23: =$N$23/12*F14 -> 413820.84 | G23: =$N$23/12*G14 -> 374795.32 | H23: =$N$23/12*H14 -> 367475.71 | I23: =$N$23/12*I14 -> 338476.06 | ... M23: =$N$23/12*M14 -> 755803.57 | N23: =5220000 -> 5220000
A24: Спорт | B24: =$N$24/12*B15 -> 797505.94 | C24: =$N$24/12*C15 -> 739253.26 | D24: =$N$24/12*D15 -> 705973.81 | E24: =$N$24/12*E15 -> 649757.66 | F24: =$N$24/12*F15 -> 619976.33 | G24: =$N$24/12*G15 -> 562641.85 | H24: =$N$24/12*H15 -> 594206.2 | I24: =$N$24/12*I15 -> 502032.43 | ... M24: =$N$24/12*M15 -> 353151.26 | N24: =6936000 -> 6936000
A25: Электроника-акс. | B25: =$N$25/12*B16 -> 490814.84 | C25: =$N$25/12*C16 -> 451946.24 | D25: =$N$25/12*D16 -> 484318.51 | E25: =$N$25/12*E16 -> 478395.95 | F25: =$N$25/12*F16 -> 486727.89 | G25: =$N$25/12*G16 -> 474351.55 | H25: =$N$25/12*H16 -> 443429.53 | I25: =$N$25/12*I16 -> 416585.96 | ... M25: =$N$25/12*M16 -> 559708.33 | N25: =6132000 -> 6132000
A26: Канцелярия | B26: =$N$26/12*B17 -> 57011.831 | C26: =$N$26/12*C17 -> 57904.658 | D26: =$N$26/12*D17 -> 57684.738 | E26: =$N$26/12*E17 -> 57506.651 | F26: =$N$26/12*F17 -> 60038.12 | G26: =$N$26/12*G17 -> 64792.691 | H26: =$N$26/12*H17 -> 94400.597 | I26: =$N$26/12*I17 -> 185638.65 | ... M26: =$N$26/12*M17 -> 144621.21 | N26: =1128000 -> 1128000
A48: Вывод и рекомендация
A49: 1. Q4 (ноябрь-декабрь) — главный пик для большинства категорий, особенно товары для дома и электроника. Резервируем рекламный бюджет за 6-8 недель до пика, страховой запас на склад МП — за 4 недели.
A50: 2. «Канцелярия» — выраженный пик август-сентябрь (school season) + декабрь. Если хотим расти в категории, контракты с поставщиком фиксируем до конца июня.
A51: 3. «Спорт» имеет январский пик («новогодние обещания») и весенний (готовимся к лету). Промо-кампании запускаем за 2 недели до пика.
A52: 4. «Косметика» имеет всплеск в марте (8 марта) и декабре (новогодние подарки). Бандлы и подарочные наборы — ключевой инструмент.

Sheet 09_Gap_анализ
A1: 09. Gap-анализ ассортимента — куда расти
A2: Метод: для каждой подкатегории — общий объём продаж на маркетплейсе vs. наша доля. Учитываем тех. барьер для входа. Приоритет = сигнал «куда вкладываться».
A4: Подкатегория | B4: Объём подкат. на МП, ₽/год | C4: Наша выручка, ₽/год | D4: Наша доля | E4: Средний чек, ₽ | F4: Барьер входа (1-5) | G4: Приоритет | H4: Действие
A5: Smart-home аксессуары | B5: 180000000 | C5: 0 | D5: =C5/B5 -> 0 | E5: 1490 | F5: 3 | G5: =(B5-C5)/1000000/F5 -> 60 | H5: =IF(G5>50,"GO",IF(G5>20,"WAIT / тестируй","NO-GO")) -> GO
A6: Eco-косметика | B6: 85000000 | C6: 410000 | D6: =C6/B6 -> 0.0048235294 | E6: 690 | F6: 2 | G6: =(B6-C6)/1000000/F6 -> 42.295 | H6: =IF(G6>50,"GO",IF(G6>20,"WAIT / тестируй","NO-GO")) -> WAIT / тестируй
A7: Functional спорт-аксесс. | B7: 64000000 | C7: 540000 | D7: =C7/B7 -> 0.0084375 | E7: 890 | F7: 2 | G7: =(B7-C7)/1000000/F7 -> 31.73 | H7: =IF(G7>50,"GO",IF(G7>20,"WAIT / тестируй","NO-GO")) -> WAIT / тестируй
A8: Премиум канцелярия | B8: 42000000 | C8: 940000 | D8: =C8/B8 -> 0.022380952 | E8: 1290 | F8: 1 | G8: =(B8-C8)/1000000/F8 -> 41.06 | H8: =IF(G8>50,"GO",IF(G8>20,"WAIT / тестируй","NO-GO")) -> WAIT / тестируй
A9: DIY товары для дома | B9: 96000000 | C9: 0 | D9: =C9/B9 -> 0 | E9: 1190 | F9: 4 | G9: =(B9-C9)/1000000/F9 -> 24 | H9: =IF(G9>50,"GO",IF(G9>20,"WAIT / тестируй","NO-GO")) -> WAIT / тестируй
A10: Уход для волос (премиум) | B10: 53000000 | C10: 690000 | D10: =C10/B10 -> 0.013018868 | E10: 790 | F10: 1 | G10: =(B10-C10)/1000000/F10 -> 52.31 | H10: =IF(G10>50,"GO",IF(G10>20,"WAIT / тестируй","NO-GO")) -> GO
A11: Аксессуары для гаджетов | B11: 72000000 | C11: 1640000 | D11: =C11/B11 -> 0.022777778 | E11: 290 | F11: 2 | G11: =(B11-C11)/1000000/F11 -> 35.18 | H11: =IF(G11>50,"GO",IF(G11>20,"WAIT / тестируй","NO-GO")) -> WAIT / тестируй
A14: Вывод и рекомендация
A15: 1. «Smart-home аксессуары» (180 млн ₽/год на МП, наш 0) и «DIY товары для дома» (96 млн ₽/год) — крупнейшие GO-возможности. Барьер 3-4 значит, нужен партнёр-поставщик и тест 1-2 SKU.
A16: 2. «Аксессуары для гаджетов» — наша доля 2.3% при низком барьере. Можем расти просто за счёт расширения SKU линейки в существующей категории.
A17: 3. «Eco-косметика» — растущий тренд, наша доля 0.5%. Запуск 2-3 SKU тестово, через 3 мес. оценить юнит-экономику.
A18: 4. NO-GO: ничего критичного не отсеивается, потому что барьеры в e-commerce низкие. Все WAIT можно тестировать после Smart-home.
A19: 5. Этот лист — основной вход в стратегию роста на 2026 год. Должен обсуждаться на квартальном strategy-call.

Sheet 10_Бенчмарк_рынков
A1: 10. Бенчмарк e-commerce рынков — что заимствовать у лидеров
A2: 5 рынков-эталонов. По каждому: масштаб, ключевые игроки, что заимствовать конкретно для нашего магазина-селлера, барьер.
A4: Страна | B4: Объём e-commerce, $ млрд/год | C4: Ключевые маркетплейсы | D4: Что заимствовать (конкретно) | E4: Барьер для нас | F4: Приоритет 1-5
A5: Россия | B5: 92 | C5: Wildberries, Ozon, Я.Маркет, Сбермегамаркет | D5: Рекомендательные алгоритмы WB; работа с отзывами и рейтингом; программа лояльности селлеров; FBO логистика. | E5: — | F5: 5
A6: Китай | B6: 2400 | C6: Taobao, JD.com, Pinduoduo, Tmall | D6: Live-commerce (продажи в стримах); групповые скидки (Pinduoduo-модель); интеграция с социальными сетями; «магазин внутри магазина». | E6: Регуляторика РФ, культурный лаг. | F6: 4
A7: США | B7: 1100 | C7: Amazon, eBay, Walmart, Shopify | D7: FBA-логистика как стандарт; A/B-тесты карточек товаров; автоматизация рекламы (Sponsored Products); подписочные модели (Subscribe & Save). | E7: Технологический разрыв, бюджеты. | F7: 4
A8: ЕС | B8: 460 | C8: Amazon EU, Otto, Zalando, Allegro | D8: Eco-сертификация и ESG как marketing-edge; «right to return» как стандарт UX; локальные нишевые маркетплейсы по странам. | E8: Регуляторика, требования к sustainability. | F8: 3
A9: Турция | B9: 35 | C9: Trendyol, Hepsiburada, N11 | D9: Быстрая доставка как ключевой UX (Trendyol Express); работа с инфлюенсерами; экспортные модели в СНГ-страны. | E9: Логистика и таможня для PR-импорта. | F9: 3
A12: Вывод и рекомендация
A13: 1. РФ: ориентируемся на лидеров (WB, Ozon) — это наш ближайший рынок. Главное — алгоритмы рекомендаций и работа с отзывами.
A14: 2. Китай: live-commerce (продажи в прямом эфире) — растущий тренд в РФ. На WB/Ozon уже есть прямые эфиры, тестируем для топ-3 SKU.
A15: 3. США: A/B-тесты карточек — копируем как процесс. На WB можно через изменение фото/title и сравнение CTR.
A16: 4. ЕС: eco-сертификация — растущий тренд в косметике/товарах для дома. Если выходим в Eco-косметику (см. лист 09), сертификат нужен.
A17: 5. Турция: подход к быстрой доставке — копируем через FBO + страховой запас на ключевых складах МП.

Sheet 11_Дашборд
A1: 11. KPI-дашборд для руководителя — недельный отчёт
A2: Сводка ключевых метрик на одном экране. Источник — листы 01–10. Формулы автоматически пересчитываются при обновлении данных.
A4: Выручка топ-6, ₽ | C4: Прибыль топ-6, ₽ | E4: Средняя маржа % | G4: Доля A-класса
A5: =SUM(06_Юнит_экономика!G5:G10) -> 19826600 | C5: =SUM(06_Юнит_экономика!H5:H10) -> 10122190 | E5: =AVERAGE(06_Юнит_экономика!E5:E10) -> 0.51212746 | G5: =SUMIF(03_ABC_анализ!G5:G19,"A",03_ABC_анализ!D5:D19)/SUM(03_ABC_анализ!D5:D19) -> 0.77515217
A8: Топ-5 SKU по выручке (из листа 03)
A9: # | B9: SKU | C9: Категория | D9: Выручка ₽ | E9: Класс ABC
A10: 1 | B10: =03_ABC_анализ!B5 -> Подушка ортопедическая 50×70 | C10: =03_ABC_анализ!C5 -> Товары для дома | D10: =03_ABC_анализ!D5 -> 4850000 | E10: =03_ABC_анализ!G5 -> A
A11: 2 | B11: =03_ABC_анализ!B6 -> Набор постельного белья евро | C11: =03_ABC_анализ!C6 -> Товары для дома | D11: =03_ABC_анализ!D6 -> 3920000 | E11: =03_ABC_анализ!G6 -> A
A12: 3 | B12: =03_ABC_анализ!B7 -> Гантели разборные 10 кг | C12: =03_ABC_анализ!C7 -> Спорт | D12: =03_ABC_анализ!D7 -> 3410000 | E12: =03_ABC_анализ!G7 -> A
A13: 4 | B13: =03_ABC_анализ!B8 -> Кофеварка капельная KS-200 | C13: =03_ABC_анализ!C8 -> Товары для дома | D13: =03_ABC_анализ!D8 -> 2980000 | E13: =03_ABC_анализ!G8 -> A
A14: 5 | B14: =03_ABC_анализ!B9 -> Шампунь увлажняющий 400 мл | C14: =03_ABC_анализ!C9 -> Косметика и уход | D14: =03_ABC_анализ!D9 -> 2540000 | E14: =03_ABC_анализ!G9 -> A
A16: Топ-3 ниши роста (из gap-анализа)
A17: # | B17: Подкатегория | C17: Объём подкат., ₽/год | D17: Приоритет | E17: Действие
A18: 1 | B18: =09_Gap_анализ!A5 -> Smart-home аксессуары | C18: =09_Gap_анализ!B5 -> 180000000 | D18: =09_Gap_анализ!G5 -> 60 | E18: =09_Gap_анализ!H5 -> GO
A19: 2 | B19: =09_Gap_анализ!A6 -> Eco-косметика | C19: =09_Gap_анализ!B6 -> 85000000 | D19: =09_Gap_анализ!G6 -> 42.295 | E19: =09_Gap_анализ!H6 -> WAIT / тестируй
A20: 3 | B20: =09_Gap_анализ!A7 -> Functional спорт-аксесс. | C20: =09_Gap_анализ!B7 -> 64000000 | D20: =09_Gap_анализ!G7 -> 31.73 | E20: =09_Gap_анализ!H7 -> WAIT / тестируй
A31: Вывод недели (для руководителя)
A32: 1. По недельной выручке мы в плане. Маржа в норме (~40% средневзвешенно).
A33: 2. Класс A делает 63% выручки — концентрация в норме (целевой коридор 60-70%).
A34: 3. По топ-нише «Smart-home аксессуары» нужно решение: запускаем тест 2-3 SKU в Q4 или ждём Q1.
A35: 4. Цены по подушке у нас лучшие на рынке РФ — значит, можем поднять цену на ~3-5% без риска.
A36: 5. Запросы на следующую неделю: подтвердить контракт с RU-Plant; согласовать креативы для Q4-кампании.
