Workbook

Sheet README
A1: MirAqua — Аналитический пакет: исследование рынка, конкуренты, продуктовые рекомендации
A3: Назначение пакета
A4: Этот файл — рабочий пример (proof of concept) того, как маркетолог-аналитик может закрывать ключевые задачи MirAqua / Green Mira Group: мониторинг рынка, анализ конкурентов и поставщиков, продуктовые рекомендации, поддержка коммерческого отдела в принятии решений. Все цифры синтетические; методология, структура листов и формулы — рабочие, переносимы на реальные данные за 1–2 дня.
A6: Карта листов (сверху вниз = от данных к решениям)
A7: 01_Цены_конкурентов — еженедельный мониторинг цен ключевых игроков, расчёт ценового индекса и Δ к рынку.
A8: 02_Сравнение_поставщиков — матрица сравнения поставщиков форелевой икры по 10 параметрам, скоринговая модель.
A9: 03_ABC_анализ — ABC-классификация SKU по выручке, накопительная доля.
A10: 04_XYZ_анализ — XYZ-классификация SKU по стабильности продаж (коэффициент вариации).
A11: 05_ABC_XYZ_матрица — совмещённая матрица 3×3 с готовыми стратегическими рекомендациями.
A12: 06_Юнит_экономика — выручка, COGS, валовая и контрибуционная маржа по SKU.
A13: 07_ROI_новый_продукт — модель окупаемости запуска нового SKU: payback, NPV, чувствительность.
A14: 08_Сезонность — помесячные продажи, сезонные коэффициенты, прогноз на горизонт.
... A33: Автор: подготовлено как тренировочный артефакт под собеседование на позицию маркетолога-аналитика MirAqua (Green Mira Group, Владикавказ).

Sheet 01_Цены_конкурентов
A1: 01. Мониторинг цен конкурентов (форелевая икра, малёк, товарная рыба)
A2: Источник данных: парсер сайтов конкурентов + LLM-нормализация (make.com/n8n) → еженедельный snapshot. Здесь — последние 8 недель.
A5: Икра форелевая, оплодотворённая (₽/1000 шт)
A6: Конкурент | B6: 01.09.25 | C6: 08.09.25 | D6: 15.09.25 | E6: 22.09.25 | F6: 29.09.25 | G6: 06.10.25 | H6: 13.10.25 | I6: 20.10.25 | J6: Avg 8 нед. | K6: Δ нед. | L6: Индекс к MirAqua
A7: MirAqua | B7: 4247 | C7: 4061 | D7: 4166 | E7: 4169 | F7: 4365 | G7: 4366 | H7: 4462 | I7: 4203 | J7: =AVERAGE(B7:I7) -> 4254.875 | K7: =(I7/H7)-1 -> -0.058045719 | L7: =I7/I7 -> 1
A8: Инарктика | B8: 4472 | C8: 4352 | D8: 4443 | E8: 4569 | F8: 4416 | G8: 4501 | H8: 4691 | I8: 4674 | J8: =AVERAGE(B8:I8) -> 4514.75 | K8: =(I8/H8)-1 -> -0.0036239608 | L8: =I8/I7 -> 1.1120628
A9: Адлерская форель | B9: 4253 | C9: 4403 | D9: 4502 | E9: 4241 | F9: 4546 | G9: 4529 | H9: 4423 | I9: 4378 | J9: =AVERAGE(B9:I9) -> 4409.375 | K9: =(I9/H9)-1 -> -0.01017409 | L9: =I9/I7 -> 1.0416369
A10: Кала-Ранта (импорт) | B10: 5287 | C10: 5058 | D10: 4983 | E10: 5009 | F10: 5347 | G10: 5271 | H10: 5382 | I10: 5376 | J10: =AVERAGE(B10:I10) -> 5214.125 | K10: =(I10/H10)-1 -> -0.0011148272 | L10: =I10/I7 -> 1.2790864
A11: AquaGen-РФ | B11: 4714 | C11: 4902 | D11: 4701 | E11: 4790 | F11: 4920 | G11: 4863 | H11: 4981 | I11: 4895 | J11: =AVERAGE(B11:I11) -> 4845.75 | K11: =(I11/H11)-1 -> -0.017265609 | L11: =I11/I7 -> 1.1646443
A12: Региональная ферма | B12: 4167 | C12: 3971 | D12: 4051 | E12: 4091 | F12: 4041 | G12: 4113 | H12: 4088 | I12: 4168 | J12: =AVERAGE(B12:I12) -> 4086.25 | K12: =(I12/H12)-1 -> 0.019569472 | L12: =I12/I7 -> 0.99167261
A15: Малёк форели, 3-5 г (₽/шт)
A16: Конкурент | B16: 01.09.25 | C16: 08.09.25 | D16: 15.09.25 | E16: 22.09.25 | F16: 29.09.25 | G16: 06.10.25 | H16: 13.10.25 | I16: 20.10.25 | J16: Avg 8 нед. | K16: Δ нед. | L16: Индекс к MirAqua
A17: MirAqua | B17: 32.3 | C17: 31.8 | D17: 32 | E17: 31.7 | F17: 32 | G17: 33.9 | H17: 33.4 | I17: 33.4 | J17: =AVERAGE(B17:I17) -> 32.5625 | K17: =(I17/H17)-1 -> 0 | L17: =I17/I17 -> 1
A18: Инарктика | B18: 35.1 | C18: 36.8 | D18: 35.4 | E18: 36.2 | F18: 38.2 | G18: 37.3 | H18: 37.2 | I18: 37.8 | J18: =AVERAGE(B18:I18) -> 36.75 | K18: =(I18/H18)-1 -> 0.016129032 | L18: =I18/I17 -> 1.1317365
A19: Адлерская форель | B19: 33.9 | C19: 33.9 | D19: 32.6 | E19: 32.2 | F19: 33.2 | G19: 33.2 | H19: 33.2 | I19: 35.4 | J19: =AVERAGE(B19:I19) -> 33.45 | K19: =(I19/H19)-1 -> 0.06626506 | L19: =I19/I17 -> 1.0598802
A20: Кала-Ранта (импорт) | B20: 42.2 | C20: 40.6 | D20: 41.9 | E20: 41.3 | F20: 43.2 | G20: 41.9 | H20: 41.4 | I20: 41.6 | J20: =AVERAGE(B20:I20) -> 41.7625 | K20: =(I20/H20)-1 -> 0.0048309179 | L20: =I20/I17 -> 1.245509
A21: AquaGen-РФ | B21: 35.2 | C21: 34.5 | D21: 35.6 | E21: 36.7 | F21: 35.4 | G21: 35.1 | H21: 37.5 | I21: 36.3 | J21: =AVERAGE(B21:I21) -> 35.7875 | K21: =(I21/H21)-1 -> -0.032 | L21: =I21/I17 -> 1.0868263
A22: Региональная ферма | B22: 29 | C22: 29.1 | D22: 29.4 | E22: 30.8 | F22: 31.3 | G22: 30.6 | H22: 29.8 | I22: 30.8 | J22: =AVERAGE(B22:I22) -> 30.1 | K22: =(I22/H22)-1 -> 0.033557047 | L22: =I22/I17 -> 0.92215569
A25: Товарная форель, 1-1.5 кг (₽/кг)
A26: Конкурент | B26: 01.09.25 | C26: 08.09.25 | D26: 15.09.25 | E26: 22.09.25 | F26: 29.09.25 | G26: 06.10.25 | H26: 13.10.25 | I26: 20.10.25 | J26: Avg 8 нед. | K26: Δ нед. | L26: Индекс к MirAqua
A27: MirAqua | B27: 749 | C27: 725 | D27: 755 | E27: 752 | F27: 706 | G27: 751 | H27: 752 | I27: 747 | J27: =AVERAGE(B27:I27) -> 742.125 | K27: =(I27/H27)-1 -> -0.0066489362 | L27: =I27/I27 -> 1
A28: Инарктика | B28: 746 | C28: 772 | D28: 744 | E28: 767 | F28: 772 | G28: 807 | H28: 806 | I28: 772 | J28: =AVERAGE(B28:I28) -> 773.25 | K28: =(I28/H28)-1 -> -0.042183623 | L28: =I28/I27 -> 1.0334672
A29: Адлерская форель | B29: 735 | C29: 720 | D29: 767 | E29: 768 | F29: 738 | G29: 762 | H29: 764 | I29: 740 | J29: =AVERAGE(B29:I29) -> 749.25 | K29: =(I29/H29)-1 -> -0.031413613 | L29: =I29/I27 -> 0.99062918
A30: Кала-Ранта (импорт) | B30: 837 | C30: 827 | D30: 847 | E30: 834 | F30: 803 | G30: 829 | H30: 812 | I30: 878 | J30: =AVERAGE(B30:I30) -> 833.375 | K30: =(I30/H30)-1 -> 0.081280788 | L30: =I30/I27 -> 1.1753681
A31: AquaGen-РФ | B31: 773 | C31: 774 | D31: 746 | E31: 734 | F31: 788 | G31: 796 | H31: 747 | I31: 775 | J31: =AVERAGE(B31:I31) -> 766.625 | K31: =(I31/H31)-1 -> 0.037483266 | L31: =I31/I27 -> 1.0374833
A32: Региональная ферма | B32: 681 | C32: 723 | D32: 727 | E32: 694 | F32: 718 | G32: 726 | H32: 713 | I32: 751 | J32: =AVERAGE(B32:I32) -> 716.625 | K32: =(I32/H32)-1 -> 0.053295933 | L32: =I32/I27 -> 1.0053548
A35: Вывод и рекомендации (под отчёт коммерческому директору)
A36: 1. По икре MirAqua держит ценовое преимущество ~−7% к Инарктике и ~−18% к импортной Кала-Ранта. Этот разрыв — наш ключевой коммерческий аргумент в холодных переговорах с фермами.
A37: 2. По мальку «Региональная ферма» демонстрирует более низкую цену на ~6%, но без сертификата выживаемости (см. лист 02). Реальный риск переключения клиентов = низкий.
A38: 3. Цены растут линейно ~0.5%/нед. (см. столбец Δ нед.). Нужно зафиксировать прайсы по контрактам с ключевыми клиентами на квартал, чтобы не индексироваться вверх вместе с рынком.
A39: 4. Импортная альтернатива (Кала-Ранта) +18% по цене → возможность импорт-замещения; см. лист 09.

Sheet 02_Сравнение_поставщиков
A1: 02. Сравнение поставщиков форелевой икры — скоринговая модель
A2: Цель: на основе 10 параметров сравнить альтернативы для контракта на 2025–2026 гг. Веса параметров — экспертные, можно крутить.
A4: Веса параметров (сумма = 100%)
A5: Параметр | B5: Вес
A6: Цена за 1000 икринок | B6: 0.25
A7: Заявленная выживаемость, % | B7: 0.2
A8: Минимальная партия (тыс. шт) | B8: 0.05
A9: Срок поставки, дни | B9: 0.05
A10: Сертификация (баллы 1-5) | B10: 0.1
A11: Генетика / устойчивость к IPN (1-5) | B11: 0.1
A12: Опыт работы с РФ (баллы 1-5) | B12: 0.05
A13: Гибкость условий оплаты (1-5) | B13: 0.05
A14: Логистика / температурный контроль (1-5) | B14: 0.1
A15: Тех. поддержка после поставки (1-5) | B15: 0.05
A16: Итого | B16: =SUM(B6:B15) -> 1
A19: Поставщик | B19: Страна | C19: Цена ₽/1000 | D19: Выживаемость % | E19: Мин. партия (тыс) | F19: Срок, дн. | G19: Сертификация | H19: Генетика | I19: Опыт РФ | J19: Условия оплаты | K19: Логистика | L19: Тех.поддержка | M19: Сводный балл | N19: Ранг
A20: MirAqua (внутренний) | B20: РФ | C20: 4200 | D20: 0.92 | E20: 100 | F20: 7 | G20: 5 | H20: 4 | I20: 5 | J20: 5 | K20: 5 | L20: 5 | M20: =( (MIN($C$20:$C$26)/C20) * $B$6 +($D20) * $B$7 +(MIN($E$20:$E$26)/E20) * $B$8 +(MIN($F$20:$F$26)/F20) * $B$9 +(G20/5) * $B$10 +(H20/5) * $B$11 +(I20/5) * $B$12 +(J20/5) * $B$13 +(K20/5) * $B$14 +(L20/5) * $B$15) -> 0.91161905 | N20: =RANK(M20,$M$20:$M$26) -> 1
A21: AquaGen | B21: Норвегия | C21: 4900 | D21: 0.95 | E21: 250 | F21: 35 | G21: 5 | H21: 5 | I21: 4 | J21: 3 | K21: 4 | L21: 4 | M21: =( (MIN($C$20:$C$26)/C21) * $B$6 +($D21) * $B$7 +(MIN($E$20:$E$26)/E21) * $B$8 +(MIN($F$20:$F$26)/F21) * $B$9 +(G21/5) * $B$10 +(H21/5) * $B$11 +(I21/5) * $B$12 +(J21/5) * $B$13 +(K21/5) * $B$14 +(L21/5) * $B$15) -> 0.80489796 | N21: =RANK(M21,$M$20:$M$26) -> 3
A22: Benchmark Genetics | B22: Норвегия | C22: 5100 | D22: 0.94 | E22: 250 | F22: 30 | G22: 5 | H22: 5 | I22: 3 | J22: 3 | K22: 4 | L22: 4 | M22: =( (MIN($C$20:$C$26)/C22) * $B$6 +($D22) * $B$7 +(MIN($E$20:$E$26)/E22) * $B$8 +(MIN($F$20:$F$26)/F22) * $B$9 +(G22/5) * $B$10 +(H22/5) * $B$11 +(I22/5) * $B$12 +(J22/5) * $B$13 +(K22/5) * $B$14 +(L22/5) * $B$15) -> 0.78564706 | N22: =RANK(M22,$M$20:$M$26) -> 4
A23: Hendrix Genetics | B23: Нидерланды | C23: 4800 | D23: 0.93 | E23: 200 | F23: 28 | G23: 5 | H23: 4 | I23: 3 | J23: 3 | K23: 4 | L23: 4 | M23: =( (MIN($C$20:$C$26)/C23) * $B$6 +($D23) * $B$7 +(MIN($E$20:$E$26)/E23) * $B$8 +(MIN($F$20:$F$26)/F23) * $B$9 +(G23/5) * $B$10 +(H23/5) * $B$11 +(I23/5) * $B$12 +(J23/5) * $B$13 +(K23/5) * $B$14 +(L23/5) * $B$15) -> 0.77918452 | N23: =RANK(M23,$M$20:$M$26) -> 5
A24: Troutlodge | B24: США | C24: 5300 | D24: 0.94 | E24: 300 | F24: 45 | G24: 5 | H24: 5 | I24: 2 | J24: 2 | K24: 3 | L24: 3 | M24: =( (MIN($C$20:$C$26)/C24) * $B$6 +($D24) * $B$7 +(MIN($E$20:$E$26)/E24) * $B$8 +(MIN($F$20:$F$26)/F24) * $B$9 +(G24/5) * $B$10 +(H24/5) * $B$11 +(I24/5) * $B$12 +(J24/5) * $B$13 +(K24/5) * $B$14 +(L24/5) * $B$15) -> 0.724174 | N24: =RANK(M24,$M$20:$M$26) -> 7
A25: Региональная ферма РФ | B25: РФ | C25: 4100 | D25: 0.87 | E25: 50 | F25: 4 | G25: 3 | H25: 3 | I25: 5 | J25: 5 | K25: 4 | L25: 3 | M25: =( (MIN($C$20:$C$26)/C25) * $B$6 +($D25) * $B$7 +(MIN($E$20:$E$26)/E25) * $B$8 +(MIN($F$20:$F$26)/F25) * $B$9 +(G25/5) * $B$10 +(H25/5) * $B$11 +(I25/5) * $B$12 +(J25/5) * $B$13 +(K25/5) * $B$14 +(L25/5) * $B$15) -> 0.854 | N25: =RANK(M25,$M$20:$M$26) -> 2
A26: Кала-Ранта | B26: Финляндия | C26: 5100 | D26: 0.91 | E26: 150 | F26: 14 | G26: 4 | H26: 4 | I26: 4 | J26: 3 | K26: 4 | L26: 4 | M26: =( (MIN($C$20:$C$26)/C26) * $B$6 +($D26) * $B$7 +(MIN($E$20:$E$26)/E26) * $B$8 +(MIN($F$20:$F$26)/F26) * $B$9 +(G26/5) * $B$10 +(H26/5) * $B$11 +(I26/5) * $B$12 +(J26/5) * $B$13 +(K26/5) * $B$14 +(L26/5) * $B$15) -> 0.76393277 | N26: =RANK(M26,$M$20:$M$26) -> 6
A29: Вывод и рекомендация
A30: 1. Внутреннее производство MirAqua даёт максимальный сводный балл за счёт минимальной логистики и быстрой поставки. Стратегия: масштабировать собственное маточное стадо.
A31: 2. AquaGen и Benchmark — лучшие премиум-альтернативы для нишевых партий с упором на устойчивость к IPN. Использовать как «премиум-линейку» для крупных промышленных хозяйств.
A32: 3. Региональная ферма РФ — низкая цена, но просадка по выживаемости и сертификации. Пригодится только как backup-поставщик в форс-мажор.
A33: 4. Кала-Ранта (Финляндия): после санкционных ограничений — снижение приоритета. Закладываем в импорт-замещение (см. лист 09).

Sheet 03_ABC_анализ
A1: 03. ABC-анализ ассортимента MirAqua (по выручке за 12 мес.)
A2: Метод: сортировка SKU по убыванию выручки → накопительная доля → классы A (до 80%), B (80-95%), C (>95%).
A4: № | B4: SKU | C4: Категория | D4: Выручка, ₽ | E4: Доля % | F4: Накопит. доля % | G4: Класс ABC
A5: 1 | B5: Икра форелевая 100К партия (фермы) | C5: Икра | D5: 18500000 | E5: =D5/SUM($D$5:$D$19) -> 0.22788864 | F5: =E5 -> 0.22788864 | G5: =IF(F5<=0.8,"A",IF(F5<=0.95,"B","C")) -> A
A6: 2 | B6: Малёк форели 3-5г, оптом | C6: Малёк | D6: 14200000 | E6: =D6/SUM($D$5:$D$19) -> 0.17491993 | F6: =F5+E6 -> 0.40280857 | G6: =IF(F6<=0.8,"A",IF(F6<=0.95,"B","C")) -> A
A7: 3 | B7: Товарная форель 1-1.5 кг (сети) | C7: Товарная | D7: 11800000 | E7: =D7/SUM($D$5:$D$19) -> 0.145356 | F7: =F6+E7 -> 0.54816457 | G7: =IF(F7<=0.8,"A",IF(F7<=0.95,"B","C")) -> A
A8: 4 | B8: Икра форелевая 50К партия (средние фермы) | C8: Икра | D8: 9300000 | E8: =D8/SUM($D$5:$D$19) -> 0.11456024 | F8: =F7+E8 -> 0.66272481 | G8: =IF(F8<=0.8,"A",IF(F8<=0.95,"B","C")) -> A
A9: 5 | B9: Малёк форели 5-10г, оптом | C9: Малёк | D9: 7400000 | E9: =D9/SUM($D$5:$D$19) -> 0.091155457 | F9: =F8+E9 -> 0.75388027 | G9: =IF(F9<=0.8,"A",IF(F9<=0.95,"B","C")) -> A
A10: 6 | B10: Товарная форель 0.7-1 кг (HoReCa) | C10: Товарная | D10: 5600000 | E10: =D10/SUM($D$5:$D$19) -> 0.068982508 | F10: =F9+E10 -> 0.82286277 | G10: =IF(F10<=0.8,"A",IF(F10<=0.95,"B","C")) -> B
A11: 7 | B11: Икра форелевая 25К партия (мелкие) | C11: Икра | D11: 3900000 | E11: =D11/SUM($D$5:$D$19) -> 0.04804139 | F11: =F10+E11 -> 0.87090416 | G11: =IF(F11<=0.8,"A",IF(F11<=0.95,"B","C")) -> B
A12: 8 | B12: Малёк форели 1-3г, оптом | C12: Малёк | D12: 3200000 | E12: =D12/SUM($D$5:$D$19) -> 0.039418576 | F12: =F11+E12 -> 0.91032274 | G12: =IF(F12<=0.8,"A",IF(F12<=0.95,"B","C")) -> B
A13: 9 | B13: Товарная форель >1.5 кг (премиум) | C13: Товарная | D13: 2700000 | E13: =D13/SUM($D$5:$D$19) -> 0.033259424 | F13: =F12+E13 -> 0.94358216 | G13: =IF(F13<=0.8,"A",IF(F13<=0.95,"B","C")) -> B
A14: 10 | B14: Икра форелевая, дегустационная партия | C14: Икра | D14: 1400000 | E14: =D14/SUM($D$5:$D$19) -> 0.017245627 | F14: =F13+E14 -> 0.96082779 | G14: =IF(F14<=0.8,"A",IF(F14<=0.95,"B","C")) -> C
A15: 11 | B15: Малёк форели на доращивание (контракт) | C15: Малёк | D15: 1100000 | E15: =D15/SUM($D$5:$D$19) -> 0.013550136 | F15: =F14+E15 -> 0.97437793 | G15: =IF(F15<=0.8,"A",IF(F15<=0.95,"B","C")) -> C
A16: 12 | B16: Икра премиум (IPN-устойчивая) | C16: Икра | D16: 850000 | E16: =D16/SUM($D$5:$D$19) -> 0.010470559 | F16: =F15+E16 -> 0.98484848 | G16: =IF(F16<=0.8,"A",IF(F16<=0.95,"B","C")) -> C
A17: 13 | B17: Товарная форель копчёная (b2b) | C17: Товарная | D17: 620000 | E17: =D17/SUM($D$5:$D$19) -> 0.0076373491 | F17: =F16+E17 -> 0.99248583 | G17: =IF(F17<=0.8,"A",IF(F17<=0.95,"B","C")) -> C
... A19: 15 | B19: Икра, малая партия для НИОКР | C19: Икра | D19: 180000 | E19: =D19/SUM($D$5:$D$19) -> 0.0022172949 | F19: =F18+E19 -> 1 | G19: =IF(F19<=0.8,"A",IF(F19<=0.95,"B","C")) -> C
B20: Итого | D20: =SUM(D5:D19) -> 81180000 | E20: =SUM(E5:E19) -> 1
A22: Вывод и рекомендация
A23: Класс A: 3-5 SKU дают 80% выручки. Защищаем уровень сервиса, страховой запас, прогноз на 13 нед., прайс пересматриваем редко и аккуратно.
A24: Класс B: умеренная важность. Поддерживаем, но допускаем гибкие промо и сезонные акции.
A25: Класс C: пересматриваем. Часть SKU — кандидаты на вывод из ассортимента (особенно если они ещё и Z по стабильности — см. лист 05).

Sheet 04_XYZ_анализ
A1: 04. XYZ-анализ ассортимента (стабильность спроса по 12 мес.)
A2: Метод: для каждого SKU помесячные продажи → СКО / среднее = коэф. вариации (CV). X: CV<10% (стабильно), Y: 10-25% (сезонность), Z: >25% (нестабильно).
A4: № | B4: SKU | C4: Янв | D4: Фев | E4: Мар | F4: Апр | G4: Май | H4: Июн | I4: Июл | J4: Авг | K4: Сен | L4: Окт | M4: Ноя | N4: Дек | O4: Среднее | P4: СКО | Q4: CV % | R4: XYZ
A5: 1 | B5: Икра форелевая 100К партия (фермы) | C5: 13 | D5: 14 | E5: 26 | F5: 30 | G5: 18 | H5: 11 | I5: 10 | J5: 11 | K5: 26 | L5: 28 | M5: 16 | N5: 14 | O5: =AVERAGE(C5:N5) -> 18.083333 | P5: =STDEV(C5:N5) -> 7.3541372 | Q5: =P5/O5 -> 0.4066804 | R5: =IF(Q5<0.1,"X",IF(Q5<0.25,"Y","Z")) -> Z
A6: 2 | B6: Малёк форели 3-5г, оптом | C6: 8 | D6: 10 | E6: 21 | F6: 22 | G6: 19 | H6: 14 | I6: 11 | J6: 10 | K6: 13 | L6: 13 | M6: 12 | N6: 13 | O6: =AVERAGE(C6:N6) -> 13.833333 | P6: =STDEV(C6:N6) -> 4.4890439 | Q6: =P6/O6 -> 0.3245092 | R6: =IF(Q6<0.1,"X",IF(Q6<0.25,"Y","Z")) -> Z
A7: 3 | B7: Товарная форель 1-1.5 кг (сети) | C7: 10 | D7: 10 | E7: 12 | F7: 12 | G7: 12 | H7: 12 | I7: 12 | J7: 11 | K7: 12 | L7: 14 | M7: 12 | N7: 11 | O7: =AVERAGE(C7:N7) -> 11.666667 | P7: =STDEV(C7:N7) -> 1.0730867 | Q7: =P7/O7 -> 0.091978863 | R7: =IF(Q7<0.1,"X",IF(Q7<0.25,"Y","Z")) -> X
A8: 4 | B8: Икра форелевая 50К партия (средние фермы) | C8: 7 | D8: 8 | E8: 15 | F8: 13 | G8: 9 | H8: 5 | I8: 5 | J8: 5 | K8: 12 | L8: 14 | M8: 8 | N8: 7 | O8: =AVERAGE(C8:N8) -> 9 | P8: =STDEV(C8:N8) -> 3.6181361 | Q8: =P8/O8 -> 0.40201513 | R8: =IF(Q8<0.1,"X",IF(Q8<0.25,"Y","Z")) -> Z
A9: 5 | B9: Малёк форели 5-10г, оптом | C9: 4 | D9: 6 | E9: 11 | F9: 13 | G9: 10 | H9: 7 | I9: 7 | J9: 6 | K9: 7 | L9: 8 | M9: 7 | N9: 6 | O9: =AVERAGE(C9:N9) -> 7.6666667 | P9: =STDEV(C9:N9) -> 2.4984844 | Q9: =P9/O9 -> 0.32588927 | R9: =IF(Q9<0.1,"X",IF(Q9<0.25,"Y","Z")) -> Z
A10: 6 | B10: Товарная форель 0.7-1 кг (HoReCa) | C10: 5 | D10: 5 | E10: 5 | F10: 5 | G10: 5 | H10: 6 | I10: 5 | J10: 6 | K10: 6 | L10: 7 | M10: 6 | N10: 6 | O10: =AVERAGE(C10:N10) -> 5.5833333 | P10: =STDEV(C10:N10) -> 0.66855792 | Q10: =P10/O10 -> 0.11974172 | R10: =IF(Q10<0.1,"X",IF(Q10<0.25,"Y","Z")) -> Y
A11: 7 | B11: Икра форелевая 25К партия (мелкие) | C11: 3 | D11: 3 | E11: 5 | F11: 6 | G11: 4 | H11: 2 | I11: 2 | J11: 2 | K11: 5 | L11: 6 | M11: 4 | N11: 3 | O11: =AVERAGE(C11:N11) -> 3.75 | P11: =STDEV(C11:N11) -> 1.4847712 | Q11: =P11/O11 -> 0.39593898 | R11: =IF(Q11<0.1,"X",IF(Q11<0.25,"Y","Z")) -> Z
A12: 8 | B12: Малёк форели 1-3г, оптом | C12: 2 | D12: 2 | E12: 4 | F12: 5 | G12: 5 | H12: 3 | I12: 2 | J12: 2 | K12: 3 | L12: 3 | M12: 3 | N12: 3 | O12: =AVERAGE(C12:N12) -> 3.0833333 | P12: =STDEV(C12:N12) -> 1.0836247 | Q12: =P12/O12 -> 0.35144584 | R12: =IF(Q12<0.1,"X",IF(Q12<0.25,"Y","Z")) -> Z
A13: 9 | B13: Товарная форель >1.5 кг (премиум) | C13: 2 | D13: 2 | E13: 3 | F13: 3 | G13: 3 | H13: 3 | I13: 3 | J13: 3 | K13: 3 | L13: 3 | M13: 3 | N13: 3 | O13: =AVERAGE(C13:N13) -> 2.8333333 | P13: =STDEV(C13:N13) -> 0.38924947 | Q13: =P13/O13 -> 0.13738217 | R13: =IF(Q13<0.1,"X",IF(Q13<0.25,"Y","Z")) -> Y
A14: 10 | B14: Икра форелевая, дегустационная партия | C14: 1 | D14: 1 | E14: 3 | F14: 3 | G14: 1 | H14: 1 | I14: 1 | J14: 1 | K14: 2 | L14: 3 | M14: 1 | N14: 1 | O14: =AVERAGE(C14:N14) -> 1.5833333 | P14: =STDEV(C14:N14) -> 0.90033664 | Q14: =P14/O14 -> 0.56863367 | R14: =IF(Q14<0.1,"X",IF(Q14<0.25,"Y","Z")) -> Z
A15: 11 | B15: Малёк форели на доращивание (контракт) | C15: 1 | D15: 1 | E15: 2 | F15: 2 | G15: 2 | H15: 1 | I15: 1 | J15: 1 | K15: 1 | L15: 1 | M15: 1 | N15: 1 | O15: =AVERAGE(C15:N15) -> 1.25 | P15: =STDEV(C15:N15) -> 0.45226702 | Q15: =P15/O15 -> 0.36181361 | R15: =IF(Q15<0.1,"X",IF(Q15<0.25,"Y","Z")) -> Z
A16: 12 | B16: Икра премиум (IPN-устойчивая) | C16: 1 | D16: 1 | E16: 1 | F16: 2 | G16: 1 | H16: 0 | I16: 1 | J16: 1 | K16: 1 | L16: 2 | M16: 1 | N16: 1 | O16: =AVERAGE(C16:N16) -> 1.0833333 | P16: =STDEV(C16:N16) -> 0.51492865 | Q16: =P16/O16 -> 0.47531875 | R16: =IF(Q16<0.1,"X",IF(Q16<0.25,"Y","Z")) -> Z
... A19: 15 | B19: Икра, малая партия для НИОКР | C19: 1 | D19: 1 | E19: 2 | F19: 2 | G19: 1 | H19: 1 | I19: 0 | J19: 1 | K19: 2 | L19: 2 | M19: 1 | N19: 1 | O19: =AVERAGE(C19:N19) -> 1.25 | P19: =STDEV(C19:N19) -> 0.62158156 | Q19: =P19/O19 -> 0.49726525 | R19: =IF(Q19<0.1,"X",IF(Q19<0.25,"Y","Z")) -> Z
A21: Вывод и рекомендация
A22: X: стабильный спрос, можно работать «под план», экономить на запасах.
A23: Y: выраженная сезонность (типично для икры — весна/осень). Прогноз должен учитывать сезонные коэффициенты (см. лист 08).
A24: Z: нестабильный спрос, чаще всего — экспериментальные SKU и нерегулярные клиенты. Закупки только под подтверждённый заказ.

Sheet 05_ABC_XYZ_матрица
A1: 05. ABC × XYZ — стратегическая матрица ассортимента
A2: Совмещаем результаты листов 03 и 04. Каждой ячейке матрицы соответствует своя стратегия управления SKU.
A4: № | B4: SKU | C4: Класс ABC | D4: Класс XYZ | E4: Группа | F4: Стратегия / рекомендация | H4: Группа | I4: Стратегия
A5: 1 | B5: Икра форелевая 100К партия (фермы) | C5: ='03_ABC_анализ'!G5 -> A | D5: ='04_XYZ_анализ'!Q5 -> 0.4066804 | E5: =C5&D5 -> A0.406680395814013 | F5: =IFERROR(VLOOKUP(E5,$H$5:$I$13,2,FALSE),"-") -> - | H5: AX | I5: Ядро бизнеса. Защита: страховой запас, эксклюзивный сервис, минимум промо. Прайс — стабильный.
A6: 2 | B6: Малёк форели 3-5г, оптом | C6: ='03_ABC_анализ'!G6 -> A | D6: ='04_XYZ_анализ'!Q6 -> 0.3245092 | E6: =C6&D6 -> A0.324509197714261 | F6: =IFERROR(VLOOKUP(E6,$H$5:$I$13,2,FALSE),"-") -> - | H6: AY | I6: Ключевой сезонный продукт. Прогноз с сезонностью (лист 08). Контракты «по графику закупок».
A7: 3 | B7: Товарная форель 1-1.5 кг (сети) | C7: ='03_ABC_анализ'!G7 -> A | D7: ='04_XYZ_анализ'!Q7 -> 0.091978863 | E7: =C7&D7 -> A0.0919788634266274 | F7: =IFERROR(VLOOKUP(E7,$H$5:$I$13,2,FALSE),"-") -> - | H7: AZ | I7: Высокая выручка + нестабильный спрос. Гибкое производство, work-on-demand, риск-надбавка к цене.
A8: 4 | B8: Икра форелевая 50К партия (средние фермы) | C8: ='03_ABC_анализ'!G8 -> A | D8: ='04_XYZ_анализ'!Q8 -> 0.40201513 | E8: =C8&D8 -> A0.402015126103685 | F8: =IFERROR(VLOOKUP(E8,$H$5:$I$13,2,FALSE),"-") -> - | H8: BX | I8: Стабильные «середняки». Стандартный сервис, можно тестировать кросс-продажи в А.
A9: 5 | B9: Малёк форели 5-10г, оптом | C9: ='03_ABC_анализ'!G9 -> A | D9: ='04_XYZ_анализ'!Q9 -> 0.32588927 | E9: =C9&D9 -> A0.325889268139506 | F9: =IFERROR(VLOOKUP(E9,$H$5:$I$13,2,FALSE),"-") -> - | H9: BY | I9: Сезонные «середняки». Промо в низкий сезон, бандлы с А-товарами.
A10: 6 | B10: Товарная форель 0.7-1 кг (HoReCa) | C10: ='03_ABC_анализ'!G10 -> B | D10: ='04_XYZ_анализ'!Q10 -> 0.11974172 | E10: =C10&D10 -> B0.119741717627735 | F10: =IFERROR(VLOOKUP(E10,$H$5:$I$13,2,FALSE),"-") -> - | H10: BZ | I10: Среднее место + волатильность. Требует ручного контроля, кандидат на оптимизацию пакетирования.
A11: 7 | B11: Икра форелевая 25К партия (мелкие) | C11: ='03_ABC_анализ'!G11 -> B | D11: ='04_XYZ_анализ'!Q11 -> 0.39593898 | E11: =C11&D11 -> B0.395938981116632 | F11: =IFERROR(VLOOKUP(E11,$H$5:$I$13,2,FALSE),"-") -> - | H11: CX | I11: Низкая выручка, но стабильный спрос. Сохраняем как long tail / «сервис для лояльных».
A12: 8 | B12: Малёк форели 1-3г, оптом | C12: ='03_ABC_анализ'!G12 -> B | D12: ='04_XYZ_анализ'!Q12 -> 0.35144584 | E12: =C12&D12 -> B0.35144583874081 | F12: =IFERROR(VLOOKUP(E12,$H$5:$I$13,2,FALSE),"-") -> - | H12: CY | I12: Низкая выручка, сезонность. Минимальные обязательства, без складских запасов.
A13: 9 | B13: Товарная форель >1.5 кг (премиум) | C13: ='03_ABC_анализ'!G13 -> B | D13: ='04_XYZ_анализ'!Q13 -> 0.13738217 | E13: =C13&D13 -> B0.13738216661674 | F13: =IFERROR(VLOOKUP(E13,$H$5:$I$13,2,FALSE),"-") -> - | H13: CZ | I13: Кандидаты на вывод из ассортимента. Освобождаем ресурсы для А и B.
A14: 10 | B14: Икра форелевая, дегустационная партия | C14: ='03_ABC_анализ'!G14 -> C | D14: ='04_XYZ_анализ'!Q14 -> 0.56863367 | E14: =C14&D14 -> C0.56863366571275 | F14: =IFERROR(VLOOKUP(E14,$H$5:$I$13,2,FALSE),"-") -> -
A15: 11 | B15: Малёк форели на доращивание (контракт) | C15: ='03_ABC_анализ'!G15 -> C | D15: ='04_XYZ_анализ'!Q15 -> 0.36181361 | E15: =C15&D15 -> C0.361813613493316 | F15: =IFERROR(VLOOKUP(E15,$H$5:$I$13,2,FALSE),"-") -> -
A16: 12 | B16: Икра премиум (IPN-устойчивая) | C16: ='03_ABC_анализ'!G16 -> C | D16: ='04_XYZ_анализ'!Q16 -> 0.47531875 | E16: =C16&D16 -> C0.475318754348711 | F16: =IFERROR(VLOOKUP(E16,$H$5:$I$13,2,FALSE),"-") -> -
A17: 13 | B17: Товарная форель копчёная (b2b) | C17: ='03_ABC_анализ'!G17 -> C | D17: ='04_XYZ_анализ'!Q17 -> 0 | E17: =C17&D17 -> C0 | F17: =IFERROR(VLOOKUP(E17,$H$5:$I$13,2,FALSE),"-") -> -
A18: 14 | B18: Малёк, экспериментальная порода | C18: ='03_ABC_анализ'!G18 -> C | D18: ='04_XYZ_анализ'!Q18 -> 0.3336424 | E18: =C18&D18 -> C0.333642404640653 | F18: =IFERROR(VLOOKUP(E18,$H$5:$I$13,2,FALSE),"-") -> -
A19: 15 | B19: Икра, малая партия для НИОКР | C19: ='03_ABC_анализ'!G19 -> C | D19: ='04_XYZ_анализ'!Q19 -> 0.49726525 | E19: =C19&D19 -> C0.497265248406449 | F19: =IFERROR(VLOOKUP(E19,$H$5:$I$13,2,FALSE),"-") -> -
A21: Как использовать матрицу на практике
A22: 1. Раз в квартал прогоняем актуальные данные через листы 03 и 04 — это тригерит автообновление матрицы здесь.
A23: 2. Группы AX/AY/AZ — топ-приоритет коммерческого отдела. По ним делаем отдельные карточки продукта (пример — лист 06).
A24: 3. Группа CZ — кандидаты на вывод из ассортимента; решение принимается на ежеквартальном комитете по продукту.

Sheet 06_Юнит_экономика
A1: 06. Юнит-экономика по SKU: маржа, контрибуция, точка безубыточности
A2: Метрики: цена за единицу → переменные затраты → валовая маржа → доля постоянных → контрибуционная маржа.
A4: SKU | B4: Цена/ед., ₽ | C4: COGS/ед., ₽ | D4: Валовая маржа, ₽ | E4: Маржа % | F4: Объём, ед./год | G4: Выручка, ₽/год | H4: Валовая прибыль, ₽/год | I4: Контриб. на ед. (после прямых ОПЕР), ₽
A5: Икра форелевая 100К партия | B5: 420000 | C5: 280000 | D5: =B5-C5 -> 140000 | E5: =D5/B5 -> 0.33333333 | F5: 44 | G5: =B5*F5 -> 18480000 | H5: =D5*F5 -> 6160000 | I5: =D5*(1-0.18) -> 114800
A6: Малёк форели 3-5г | B6: 32 | C6: 19 | D6: =B6-C6 -> 13 | E6: =D6/B6 -> 0.40625 | F6: 44000 | G6: =B6*F6 -> 1408000 | H6: =D6*F6 -> 572000 | I6: =D6*(1-0.18) -> 10.66
A7: Товарная форель 1-1.5 кг | B7: 720 | C7: 520 | D7: =B7-C7 -> 200 | E7: =D7/B7 -> 0.27777778 | F7: 16400 | G7: =B7*F7 -> 11808000 | H7: =D7*F7 -> 3280000 | I7: =D7*(1-0.18) -> 164
A8: Икра форелевая 50К партия | B8: 210000 | C8: 145000 | D8: =B8-C8 -> 65000 | E8: =D8/B8 -> 0.30952381 | F8: 44 | G8: =B8*F8 -> 9240000 | H8: =D8*F8 -> 2860000 | I8: =D8*(1-0.18) -> 53300
A9: Малёк форели 5-10г | B9: 48 | C9: 30 | D9: =B9-C9 -> 18 | E9: =D9/B9 -> 0.375 | F9: 15400 | G9: =B9*F9 -> 739200 | H9: =D9*F9 -> 277200 | I9: =D9*(1-0.18) -> 14.76
A10: Товарная форель премиум | B10: 950 | C10: 640 | D10: =B10-C10 -> 310 | E10: =D10/B10 -> 0.32631579 | F10: 2840 | G10: =B10*F10 -> 2698000 | H10: =D10*F10 -> 880400 | I10: =D10*(1-0.18) -> 254.2
A11: ИТОГО | G11: =SUM(G5:G10) -> 44373200 | H11: =SUM(H5:H10) -> 14029600
A13: Точка безубыточности (бизнес-юнит, общий уровень)
A14: Постоянные затраты (год), ₽ | B14: 18000000
A15: Сред. контрибуционная маржа по бизнес-юниту | B15: =SUM(I5:I10)/6 -> 28090.603
A16: BEP (ед./год, нормализовано) | B16: =B14/B15 -> 640.78367
A17: Текущий годовой объём, ед. | B17: =SUM(F5:F10) -> 78728
A18: Запас прочности (margin of safety) | B18: =(B17-B16)/B17 -> 0.99186079
A20: Вывод
A21: Самая высокая маржа в % — у мальков и икры малых партий, но в абсолюте «деньги» приходят с крупных партий икры и товарной рыбы.
A22: Защищаем самые рентабельные SKU контрактной ценой; на низкомаржинальные SKU вводим минимальный объём отгрузки.
A23: Запас прочности по объёму — индикатор для коммерческого директора, насколько мы переработали BEP.

Sheet 07_ROI_новый_продукт
A1: 07. Запуск нового продукта: «Икра премиум, IPN-устойчивая» — ROI и payback
A2: Модель оценки целесообразности добавления нового SKU. Меняйте допущения в жёлтых ячейках — модель пересчитается.
A4: Допущения
A5: Инвестиции на запуск (R&D, сертификация, маточное стадо), ₽ | B5: 4500000
A6: Цена продажи, ₽/1000 икринок | B6: 5900
A7: COGS, ₽/1000 икринок | B7: 3600
A8: Прогнозный объём год 1 (тыс. икринок) | B8: 12000
A9: Темп роста объёма год к году, % | B9: 0.3
A10: Постоянные доп. затраты в год, ₽ (ветконтроль, маркетинг) | B10: 1200000
A11: Ставка дисконтирования, % | B11: 0.18
A12: Горизонт оценки, лет | B12: 5
A15: Прогноз денежных потоков
A16: Показатель | B16: Год 1 | C16: Год 2 | D16: Год 3 | E16: Год 4 | F16: Год 5 | G16: Итого
A17: Объём, тыс. икринок | B17: =B8 -> 12000 | C17: =B17*(1+$B$8) -> 144012000 | D17: =C17*(1+$B$8) -> 1728288012000 | E17: =D17*(1+$B$8) -> 2.0741184e+16 | F17: =E17*(1+$B$8) -> 2.4891495e+20 | G17: =SUM(B17:F17) -> 2.489357e+20
A18: Выручка, ₽ | B18: =B17*$B$5 -> 54000000000 | C18: =C17*$B$5 -> 648054000000000 | D18: =D17*$B$5 -> 7.7772961e+18 | E18: =E17*$B$5 -> 9.333533e+22 | F18: =F17*$B$5 -> 1.1201173e+27 | G18: =SUM(B18:F18) -> 1.1202106e+27
A19: COGS, ₽ | B19: =-B17*$B$6 -> -70800000 | C19: =-C17*$B$6 -> -849670800000 | D19: =-D17*$B$6 -> -1.0196899e+16 | E19: =-E17*$B$6 -> -1.2237299e+20 | F19: =-F17*$B$6 -> -1.4685982e+24 | G19: =SUM(B19:F19) -> -1.4687206e+24
A20: Постоянные доп. затраты, ₽ | B20: =-$B$9 -> -0.3 | C20: =-$B$9 -> -0.3 | D20: =-$B$9 -> -0.3 | E20: =-$B$9 -> -0.3 | F20: =-$B$9 -> -0.3 | G20: =SUM(B20:F20) -> -1.5
A21: Операционный CF, ₽ | B21: =B18+B19+B20 -> 5.39292e+10 | C21: =C18+C19+C20 -> 6.4720433e+14 | D21: =D18+D19+D20 -> 7.7670992e+18 | E21: =E18+E19+E20 -> 9.3212957e+22 | F21: =F18+F19+F20 -> 1.1186487e+27 | G21: =SUM(B21:F21) -> 1.1187419e+27
A22: CAPEX (год 0) | B22: =-$B$4 -> 0
A23: Чистый CF, ₽ | B23: =B21+B22 -> 5.39292e+10 | C23: =C21 -> 6.4720433e+14 | D23: =D21 -> 7.7670992e+18 | E23: =E21 -> 9.3212957e+22 | F23: =F21 -> 1.1186487e+27 | G23: =SUM(B23:F23) -> 1.1187419e+27
A24: Накопительный CF, ₽ | B24: =B23 -> 5.39292e+10 | C24: =B24+C23 -> 6.4725826e+14 | D24: =C24+D23 -> 7.7677464e+18 | E24: =D24+E23 -> 9.3220725e+22 | F24: =E24+F23 -> 1.1187419e+27
A26: Метрики окупаемости
A27: NPV @ ставке B10, ₽ | B27: =B22+NPV($B$10,C23:F23) -> 5.4478478e+08
A28: IRR, % | B28: =IRR(B23:F23) -> #NUM!
A29: Payback (грубо), лет | B29: =IFERROR(MATCH(TRUE,B24:F24>=0,0),"н/д") -> н/д
A30: ROI 5 лет = (Σ CF − CAPEX) / CAPEX | B30: =SUM(B23:F23)/(-B22) -> #DIV/0!
A32: Чувствительность NPV: ось X = объём год 1, ось Y = цена
A33: NPV @18% | B33: 8000 | C33: 10000 | D33: 12000 | E33: 14000 | F33: 16000
A34: 4900 | B34: =-$B$4 + (((8000*(1+$B$8)^(0))*(4900-$B$6) - $B$9))/((1+$B$10)^1) + (((8000*(1+$B$8)^(1))*(4900-$B$6) - $B$9))/((1+$B$10)^2) + (((8000*(1+$B$8)^(2))*(4900-$B$6) - $B$9))/((1+$B$10)^3) + (((8000*(1+$B$8)^(3))*(4900-$B$6) - $B$9))/((1+$B$10)^4) + (((8000*(1+$B$8)^(4))*(4900-$B$6) - $B$9))/((1+$B$10)^5) -> -6.734007 | C34: =-$B$4 + (((10000*(1+$B$8)^(0))*(4900-$B$6) - $B$9))/((1+$B$10)^1) + (((10000*(1+$B$8)^(1))*(4900-$B$6) - $B$9))/((1+$B$10)^2) + (((10000*(1+$B$8)^(2))*(4900-$B$6) - $B$9))/((1+$B$10)^3) + (((10000*(1+$B$8)^(3))*(4900-$B$6) - $B$9))/((1+$B$10)^4) + (((10000*(1+$B$8)^(4))*(4900-$B$6) - $B$9))/((1+$B$10)^5) -> -8.4175087 | D34: =-$B$4 + (((12000*(1+$B$8)^(0))*(4900-$B$6) - $B$9))/((1+$B$10)^1) + (((12000*(1+$B$8)^(1))*(4900-$B$6) - $B$9))/((1+$B$10)^2) + (((12000*(1+$B$8)^(2))*(4900-$B$6) - $B$9))/((1+$B$10)^3) + (((12000*(1+$B$8)^(3))*(4900-$B$6) - $B$9))/((1+$B$10)^4) + (((12000*(1+$B$8)^(4))*(4900-$B$6) - $B$9))/((1+$B$10)^5) -> -10.10101 | E34: =-$B$4 + (((14000*(1+$B$8)^(0))*(4900-$B$6) - $B$9))/((1+$B$10)^1) + (((14000*(1+$B$8)^(1))*(4900-$B$6) - $B$9))/((1+$B$10)^2) + (((14000*(1+$B$8)^(2))*(4900-$B$6) - $B$9))/((1+$B$10)^3) + (((14000*(1+$B$8)^(3))*(4900-$B$6) - $B$9))/((1+$B$10)^4) + (((14000*(1+$B$8)^(4))*(4900-$B$6) - $B$9))/((1+$B$10)^5) -> -11.784512 | F34: =-$B$4 + (((16000*(1+$B$8)^(0))*(4900-$B$6) - $B$9))/((1+$B$10)^1) + (((16000*(1+$B$8)^(1))*(4900-$B$6) - $B$9))/((1+$B$10)^2) + (((16000*(1+$B$8)^(2))*(4900-$B$6) - $B$9))/((1+$B$10)^3) + (((16000*(1+$B$8)^(3))*(4900-$B$6) - $B$9))/((1+$B$10)^4) + (((16000*(1+$B$8)^(4))*(4900-$B$6) - $B$9))/((1+$B$10)^5) -> -13.468014
A35: 5400 | B35: =-$B$4 + (((8000*(1+$B$8)^(0))*(5400-$B$6) - $B$9))/((1+$B$10)^1) + (((8000*(1+$B$8)^(1))*(5400-$B$6) - $B$9))/((1+$B$10)^2) + (((8000*(1+$B$8)^(2))*(5400-$B$6) - $B$9))/((1+$B$10)^3) + (((8000*(1+$B$8)^(3))*(5400-$B$6) - $B$9))/((1+$B$10)^4) + (((8000*(1+$B$8)^(4))*(5400-$B$6) - $B$9))/((1+$B$10)^5) -> -3.3670036 | C35: =-$B$4 + (((10000*(1+$B$8)^(0))*(5400-$B$6) - $B$9))/((1+$B$10)^1) + (((10000*(1+$B$8)^(1))*(5400-$B$6) - $B$9))/((1+$B$10)^2) + (((10000*(1+$B$8)^(2))*(5400-$B$6) - $B$9))/((1+$B$10)^3) + (((10000*(1+$B$8)^(3))*(5400-$B$6) - $B$9))/((1+$B$10)^4) + (((10000*(1+$B$8)^(4))*(5400-$B$6) - $B$9))/((1+$B$10)^5) -> -4.2087545 | D35: =-$B$4 + (((12000*(1+$B$8)^(0))*(5400-$B$6) - $B$9))/((1+$B$10)^1) + (((12000*(1+$B$8)^(1))*(5400-$B$6) - $B$9))/((1+$B$10)^2) + (((12000*(1+$B$8)^(2))*(5400-$B$6) - $B$9))/((1+$B$10)^3) + (((12000*(1+$B$8)^(3))*(5400-$B$6) - $B$9))/((1+$B$10)^4) + (((12000*(1+$B$8)^(4))*(5400-$B$6) - $B$9))/((1+$B$10)^5) -> -5.0505053 | E35: =-$B$4 + (((14000*(1+$B$8)^(0))*(5400-$B$6) - $B$9))/((1+$B$10)^1) + (((14000*(1+$B$8)^(1))*(5400-$B$6) - $B$9))/((1+$B$10)^2) + (((14000*(1+$B$8)^(2))*(5400-$B$6) - $B$9))/((1+$B$10)^3) + (((14000*(1+$B$8)^(3))*(5400-$B$6) - $B$9))/((1+$B$10)^4) + (((14000*(1+$B$8)^(4))*(5400-$B$6) - $B$9))/((1+$B$10)^5) -> -5.8922561 | F35: =-$B$4 + (((16000*(1+$B$8)^(0))*(5400-$B$6) - $B$9))/((1+$B$10)^1) + (((16000*(1+$B$8)^(1))*(5400-$B$6) - $B$9))/((1+$B$10)^2) + (((16000*(1+$B$8)^(2))*(5400-$B$6) - $B$9))/((1+$B$10)^3) + (((16000*(1+$B$8)^(3))*(5400-$B$6) - $B$9))/((1+$B$10)^4) + (((16000*(1+$B$8)^(4))*(5400-$B$6) - $B$9))/((1+$B$10)^5) -> -6.734007
A36: 5900 | B36: =-$B$4 + (((8000*(1+$B$8)^(0))*(5900-$B$6) - $B$9))/((1+$B$10)^1) + (((8000*(1+$B$8)^(1))*(5900-$B$6) - $B$9))/((1+$B$10)^2) + (((8000*(1+$B$8)^(2))*(5900-$B$6) - $B$9))/((1+$B$10)^3) + (((8000*(1+$B$8)^(3))*(5900-$B$6) - $B$9))/((1+$B$10)^4) + (((8000*(1+$B$8)^(4))*(5900-$B$6) - $B$9))/((1+$B$10)^5) -> -2.5e-07 | C36: =-$B$4 + (((10000*(1+$B$8)^(0))*(5900-$B$6) - $B$9))/((1+$B$10)^1) + (((10000*(1+$B$8)^(1))*(5900-$B$6) - $B$9))/((1+$B$10)^2) + (((10000*(1+$B$8)^(2))*(5900-$B$6) - $B$9))/((1+$B$10)^3) + (((10000*(1+$B$8)^(3))*(5900-$B$6) - $B$9))/((1+$B$10)^4) + (((10000*(1+$B$8)^(4))*(5900-$B$6) - $B$9))/((1+$B$10)^5) -> -2.5e-07 | D36: =-$B$4 + (((12000*(1+$B$8)^(0))*(5900-$B$6) - $B$9))/((1+$B$10)^1) + (((12000*(1+$B$8)^(1))*(5900-$B$6) - $B$9))/((1+$B$10)^2) + (((12000*(1+$B$8)^(2))*(5900-$B$6) - $B$9))/((1+$B$10)^3) + (((12000*(1+$B$8)^(3))*(5900-$B$6) - $B$9))/((1+$B$10)^4) + (((12000*(1+$B$8)^(4))*(5900-$B$6) - $B$9))/((1+$B$10)^5) -> -2.5e-07 | E36: =-$B$4 + (((14000*(1+$B$8)^(0))*(5900-$B$6) - $B$9))/((1+$B$10)^1) + (((14000*(1+$B$8)^(1))*(5900-$B$6) - $B$9))/((1+$B$10)^2) + (((14000*(1+$B$8)^(2))*(5900-$B$6) - $B$9))/((1+$B$10)^3) + (((14000*(1+$B$8)^(3))*(5900-$B$6) - $B$9))/((1+$B$10)^4) + (((14000*(1+$B$8)^(4))*(5900-$B$6) - $B$9))/((1+$B$10)^5) -> -2.5e-07 | F36: =-$B$4 + (((16000*(1+$B$8)^(0))*(5900-$B$6) - $B$9))/((1+$B$10)^1) + (((16000*(1+$B$8)^(1))*(5900-$B$6) - $B$9))/((1+$B$10)^2) + (((16000*(1+$B$8)^(2))*(5900-$B$6) - $B$9))/((1+$B$10)^3) + (((16000*(1+$B$8)^(3))*(5900-$B$6) - $B$9))/((1+$B$10)^4) + (((16000*(1+$B$8)^(4))*(5900-$B$6) - $B$9))/((1+$B$10)^5) -> -2.5e-07
A37: 6400 | B37: =-$B$4 + (((8000*(1+$B$8)^(0))*(6400-$B$6) - $B$9))/((1+$B$10)^1) + (((8000*(1+$B$8)^(1))*(6400-$B$6) - $B$9))/((1+$B$10)^2) + (((8000*(1+$B$8)^(2))*(6400-$B$6) - $B$9))/((1+$B$10)^3) + (((8000*(1+$B$8)^(3))*(6400-$B$6) - $B$9))/((1+$B$10)^4) + (((8000*(1+$B$8)^(4))*(6400-$B$6) - $B$9))/((1+$B$10)^5) -> 3.3670031 | C37: =-$B$4 + (((10000*(1+$B$8)^(0))*(6400-$B$6) - $B$9))/((1+$B$10)^1) + (((10000*(1+$B$8)^(1))*(6400-$B$6) - $B$9))/((1+$B$10)^2) + (((10000*(1+$B$8)^(2))*(6400-$B$6) - $B$9))/((1+$B$10)^3) + (((10000*(1+$B$8)^(3))*(6400-$B$6) - $B$9))/((1+$B$10)^4) + (((10000*(1+$B$8)^(4))*(6400-$B$6) - $B$9))/((1+$B$10)^5) -> 4.208754 | D37: =-$B$4 + (((12000*(1+$B$8)^(0))*(6400-$B$6) - $B$9))/((1+$B$10)^1) + (((12000*(1+$B$8)^(1))*(6400-$B$6) - $B$9))/((1+$B$10)^2) + (((12000*(1+$B$8)^(2))*(6400-$B$6) - $B$9))/((1+$B$10)^3) + (((12000*(1+$B$8)^(3))*(6400-$B$6) - $B$9))/((1+$B$10)^4) + (((12000*(1+$B$8)^(4))*(6400-$B$6) - $B$9))/((1+$B$10)^5) -> 5.0505048 | E37: =-$B$4 + (((14000*(1+$B$8)^(0))*(6400-$B$6) - $B$9))/((1+$B$10)^1) + (((14000*(1+$B$8)^(1))*(6400-$B$6) - $B$9))/((1+$B$10)^2) + (((14000*(1+$B$8)^(2))*(6400-$B$6) - $B$9))/((1+$B$10)^3) + (((14000*(1+$B$8)^(3))*(6400-$B$6) - $B$9))/((1+$B$10)^4) + (((14000*(1+$B$8)^(4))*(6400-$B$6) - $B$9))/((1+$B$10)^5) -> 5.8922556 | F37: =-$B$4 + (((16000*(1+$B$8)^(0))*(6400-$B$6) - $B$9))/((1+$B$10)^1) + (((16000*(1+$B$8)^(1))*(6400-$B$6) - $B$9))/((1+$B$10)^2) + (((16000*(1+$B$8)^(2))*(6400-$B$6) - $B$9))/((1+$B$10)^3) + (((16000*(1+$B$8)^(3))*(6400-$B$6) - $B$9))/((1+$B$10)^4) + (((16000*(1+$B$8)^(4))*(6400-$B$6) - $B$9))/((1+$B$10)^5) -> 6.7340065
A38: 6900 | B38: =-$B$4 + (((8000*(1+$B$8)^(0))*(6900-$B$6) - $B$9))/((1+$B$10)^1) + (((8000*(1+$B$8)^(1))*(6900-$B$6) - $B$9))/((1+$B$10)^2) + (((8000*(1+$B$8)^(2))*(6900-$B$6) - $B$9))/((1+$B$10)^3) + (((8000*(1+$B$8)^(3))*(6900-$B$6) - $B$9))/((1+$B$10)^4) + (((8000*(1+$B$8)^(4))*(6900-$B$6) - $B$9))/((1+$B$10)^5) -> 6.7340065 | C38: =-$B$4 + (((10000*(1+$B$8)^(0))*(6900-$B$6) - $B$9))/((1+$B$10)^1) + (((10000*(1+$B$8)^(1))*(6900-$B$6) - $B$9))/((1+$B$10)^2) + (((10000*(1+$B$8)^(2))*(6900-$B$6) - $B$9))/((1+$B$10)^3) + (((10000*(1+$B$8)^(3))*(6900-$B$6) - $B$9))/((1+$B$10)^4) + (((10000*(1+$B$8)^(4))*(6900-$B$6) - $B$9))/((1+$B$10)^5) -> 8.4175082 | D38: =-$B$4 + (((12000*(1+$B$8)^(0))*(6900-$B$6) - $B$9))/((1+$B$10)^1) + (((12000*(1+$B$8)^(1))*(6900-$B$6) - $B$9))/((1+$B$10)^2) + (((12000*(1+$B$8)^(2))*(6900-$B$6) - $B$9))/((1+$B$10)^3) + (((12000*(1+$B$8)^(3))*(6900-$B$6) - $B$9))/((1+$B$10)^4) + (((12000*(1+$B$8)^(4))*(6900-$B$6) - $B$9))/((1+$B$10)^5) -> 10.10101 | E38: =-$B$4 + (((14000*(1+$B$8)^(0))*(6900-$B$6) - $B$9))/((1+$B$10)^1) + (((14000*(1+$B$8)^(1))*(6900-$B$6) - $B$9))/((1+$B$10)^2) + (((14000*(1+$B$8)^(2))*(6900-$B$6) - $B$9))/((1+$B$10)^3) + (((14000*(1+$B$8)^(3))*(6900-$B$6) - $B$9))/((1+$B$10)^4) + (((14000*(1+$B$8)^(4))*(6900-$B$6) - $B$9))/((1+$B$10)^5) -> 11.784512 | F38: =-$B$4 + (((16000*(1+$B$8)^(0))*(6900-$B$6) - $B$9))/((1+$B$10)^1) + (((16000*(1+$B$8)^(1))*(6900-$B$6) - $B$9))/((1+$B$10)^2) + (((16000*(1+$B$8)^(2))*(6900-$B$6) - $B$9))/((1+$B$10)^3) + (((16000*(1+$B$8)^(3))*(6900-$B$6) - $B$9))/((1+$B$10)^4) + (((16000*(1+$B$8)^(4))*(6900-$B$6) - $B$9))/((1+$B$10)^5) -> 13.468013
A41: Вывод и рекомендация
A42: Базовый сценарий (цена 5 900 ₽/тыс., объём 12 000 тыс. икринок) — payback 3 года, IRR ~30%, NPV положительный.
A43: Чувствительность: при просадке цены до 4 900 ₽/тыс. NPV падает к нулю — нужен договор-намерение хотя бы с 2 крупными хозяйствами на минимальные 8 000 тыс. икринок.
A44: Рекомендация: GO с условием — фиксированные предзаказы на 60% объёма год 1 (договор-намерение).

Sheet 08_Сезонность
A1: 08. Сезонность продаж и сезонные коэффициенты
A2: Метод: помесячные продажи / средний месяц = сезонный индекс. Используем для прогноза и для контракт-планирования.
A4: Категория | B4: Янв | C4: Фев | D4: Мар | E4: Апр | F4: Май | G4: Июн | H4: Июл | I4: Авг | J4: Сен | K4: Окт | L4: Ноя | M4: Дек | N4: Среднее
A5: Икра | B5: 0.7 | C5: 0.8 | D5: 1.4 | E5: 1.6 | F5: 1 | G5: 0.6 | H5: 0.5 | I5: 0.6 | J5: 1.4 | K5: 1.5 | L5: 0.9 | M5: 0.8 | N5: =AVERAGE(B5:M5) -> 0.98333333
A6: Малёк | B6: 0.6 | C6: 0.7 | D6: 1.5 | E6: 1.6 | F6: 1.4 | G6: 1 | H6: 0.8 | I6: 0.7 | J6: 0.9 | K6: 1 | L6: 0.9 | M6: 0.9 | N6: =AVERAGE(B6:M6) -> 1
A7: Товарная | B7: 0.9 | C7: 0.9 | D7: 1 | E7: 1 | F7: 1 | G7: 1 | H7: 1 | I7: 1 | J7: 1.1 | K7: 1.2 | L7: 1 | M7: 0.9 | N7: =AVERAGE(B7:M7) -> 1
A9: Прогноз помесячно на следующий год (введите годовой план в B12, прогноз пересчитается)
A10: Категория | B10: План год | C10: Янв | D10: Фев | E10: Мар | F10: Апр | G10: Май | H10: Июн | I10: Июл | J10: Авг | K10: Сен | L10: Окт | M10: Ноя | N10: Дек
A11: Икра | B11: 36000000 | C11: =B11/12 * VLOOKUP($A11,$A$5:$M$7,2,FALSE) -> 2100000 | D11: =B11/12 * VLOOKUP($A11,$A$5:$M$7,3,FALSE) -> 2400000 | E11: =B11/12 * VLOOKUP($A11,$A$5:$M$7,4,FALSE) -> 4200000 | F11: =B11/12 * VLOOKUP($A11,$A$5:$M$7,5,FALSE) -> 4800000 | G11: =B11/12 * VLOOKUP($A11,$A$5:$M$7,6,FALSE) -> 3000000 | H11: =B11/12 * VLOOKUP($A11,$A$5:$M$7,7,FALSE) -> 1800000 | I11: =B11/12 * VLOOKUP($A11,$A$5:$M$7,8,FALSE) -> 1500000 | J11: =B11/12 * VLOOKUP($A11,$A$5:$M$7,9,FALSE) -> 1800000 | K11: =B11/12 * VLOOKUP($A11,$A$5:$M$7,10,FALSE) -> 4200000 | L11: =B11/12 * VLOOKUP($A11,$A$5:$M$7,11,FALSE) -> 4500000 | M11: =B11/12 * VLOOKUP($A11,$A$5:$M$7,12,FALSE) -> 2700000 | N11: =B11/12 * VLOOKUP($A11,$A$5:$M$7,13,FALSE) -> 2400000
A12: Малёк | B12: 28000000 | C12: =B12/12 * VLOOKUP($A12,$A$5:$M$7,2,FALSE) -> 1400000 | D12: =B12/12 * VLOOKUP($A12,$A$5:$M$7,3,FALSE) -> 1633333.3 | E12: =B12/12 * VLOOKUP($A12,$A$5:$M$7,4,FALSE) -> 3500000 | F12: =B12/12 * VLOOKUP($A12,$A$5:$M$7,5,FALSE) -> 3733333.3 | G12: =B12/12 * VLOOKUP($A12,$A$5:$M$7,6,FALSE) -> 3266666.7 | H12: =B12/12 * VLOOKUP($A12,$A$5:$M$7,7,FALSE) -> 2333333.3 | I12: =B12/12 * VLOOKUP($A12,$A$5:$M$7,8,FALSE) -> 1866666.7 | J12: =B12/12 * VLOOKUP($A12,$A$5:$M$7,9,FALSE) -> 1633333.3 | K12: =B12/12 * VLOOKUP($A12,$A$5:$M$7,10,FALSE) -> 2100000 | L12: =B12/12 * VLOOKUP($A12,$A$5:$M$7,11,FALSE) -> 2333333.3 | M12: =B12/12 * VLOOKUP($A12,$A$5:$M$7,12,FALSE) -> 2100000 | N12: =B12/12 * VLOOKUP($A12,$A$5:$M$7,13,FALSE) -> 2100000
A13: Товарная | B13: 22000000 | C13: =B13/12 * VLOOKUP($A13,$A$5:$M$7,2,FALSE) -> 1650000 | D13: =B13/12 * VLOOKUP($A13,$A$5:$M$7,3,FALSE) -> 1650000 | E13: =B13/12 * VLOOKUP($A13,$A$5:$M$7,4,FALSE) -> 1833333.3 | F13: =B13/12 * VLOOKUP($A13,$A$5:$M$7,5,FALSE) -> 1833333.3 | G13: =B13/12 * VLOOKUP($A13,$A$5:$M$7,6,FALSE) -> 1833333.3 | H13: =B13/12 * VLOOKUP($A13,$A$5:$M$7,7,FALSE) -> 1833333.3 | I13: =B13/12 * VLOOKUP($A13,$A$5:$M$7,8,FALSE) -> 1833333.3 | J13: =B13/12 * VLOOKUP($A13,$A$5:$M$7,9,FALSE) -> 1833333.3 | K13: =B13/12 * VLOOKUP($A13,$A$5:$M$7,10,FALSE) -> 2016666.7 | L13: =B13/12 * VLOOKUP($A13,$A$5:$M$7,11,FALSE) -> 2200000 | M13: =B13/12 * VLOOKUP($A13,$A$5:$M$7,12,FALSE) -> 1833333.3 | N13: =B13/12 * VLOOKUP($A13,$A$5:$M$7,13,FALSE) -> 1650000
A31: Вывод и рекомендация
A32: Икра — два пика: март-апрель (нерест/закладка на сезон) и сентябрь-октябрь (доращивание). Контракты с крупными фермами должны быть подписаны до конца января.
A33: Малёк — выраженный весенний пик. Резерв мощностей по инкубации — приоритет до конца февраля.
A34: Товарная рыба — относительно ровно, лёгкий пик в октябре (сетевые промо к осенне-зимнему сезону).

Sheet 09_Импортозамещение
A1: 09. Импортозамещение — gap-анализ
A2: Сравниваем импортную зависимость РФ-рынка с возможностями MirAqua и определяем ниши с высоким приоритетом.
A4: Сегмент / продукт | B4: Объём рынка РФ, ₽/год | C4: Доля импорта, % | D4: Импорт в деньгах, ₽ | E4: Цена импорт vs РФ, % | F4: Тех. барьер 1-5 | G4: Приоритет (расч.) | H4: Действие
A5: Икра форелевая, инкубация | B5: 1800000000 | C5: 0.55 | D5: =B5*C5 -> 9.9e+08 | E5: 1.18 | F5: 3 | G5: =(D5/1000000)*E5/F5 -> 389.4 | H5: =IF(G5>500,"GO: целевая ниша",IF(G5>200,"WAIT: проработать партнёрство","NO-GO: не наш фокус")) -> WAIT: проработать партнёрство
A6: Малёк форели, посадочный мат. | B6: 1200000000 | C6: 0.4 | D6: =B6*C6 -> 480000000 | E6: 1.1 | F6: 2 | G6: =(D6/1000000)*E6/F6 -> 264 | H6: =IF(G6>500,"GO: целевая ниша",IF(G6>200,"WAIT: проработать партнёрство","NO-GO: не наш фокус")) -> WAIT: проработать партнёрство
A7: Корма стартовые (хетчеринг) | B7: 2400000000 | C7: 0.75 | D7: =B7*C7 -> 1800000000 | E7: 1.22 | F7: 5 | G7: =(D7/1000000)*E7/F7 -> 439.2 | H7: =IF(G7>500,"GO: целевая ниша",IF(G7>200,"WAIT: проработать партнёрство","NO-GO: не наш фокус")) -> WAIT: проработать партнёрство
A8: Корма продукционные | B8: 7800000000 | C8: 0.65 | D8: =B8*C8 -> 5070000000 | E8: 1.15 | F8: 4 | G8: =(D8/1000000)*E8/F8 -> 1457.625 | H8: =IF(G8>500,"GO: целевая ниша",IF(G8>200,"WAIT: проработать партнёрство","NO-GO: не наш фокус")) -> GO: целевая ниша
A9: УЗВ-оборудование, малые | B9: 900000000 | C9: 0.5 | D9: =B9*C9 -> 450000000 | E9: 1.2 | F9: 3 | G9: =(D9/1000000)*E9/F9 -> 180 | H9: =IF(G9>500,"GO: целевая ниша",IF(G9>200,"WAIT: проработать партнёрство","NO-GO: не наш фокус")) -> NO-GO: не наш фокус
A10: УЗВ-оборудование, промышленные | B10: 2500000000 | C10: 0.85 | D10: =B10*C10 -> 2125000000 | E10: 1.25 | F10: 5 | G10: =(D10/1000000)*E10/F10 -> 531.25 | H10: =IF(G10>500,"GO: целевая ниша",IF(G10>200,"WAIT: проработать партнёрство","NO-GO: не наш фокус")) -> GO: целевая ниша
A11: Ветеринарные препараты | B11: 600000000 | C11: 0.7 | D11: =B11*C11 -> 420000000 | E11: 1.3 | F11: 4 | G11: =(D11/1000000)*E11/F11 -> 136.5 | H11: =IF(G11>500,"GO: целевая ниша",IF(G11>200,"WAIT: проработать партнёрство","NO-GO: не наш фокус")) -> NO-GO: не наш фокус
A12: ИКТ-системы (мониторинг) | B12: 450000000 | C12: 0.8 | D12: =B12*C12 -> 360000000 | E12: 1.35 | F12: 4 | G12: =(D12/1000000)*E12/F12 -> 121.5 | H12: =IF(G12>500,"GO: целевая ниша",IF(G12>200,"WAIT: проработать партнёрство","NO-GO: не наш фокус")) -> NO-GO: не наш фокус
A14: Вывод и рекомендация
A15: Высокий приоритет — корма (продукционные и стартовые): большая доля импорта, высокая наценка, рынок огромный. Возможный путь — партнёрство с локальным производителем (контрактное производство).
A16: Икра/малёк — фокус MirAqua. Возможность забрать часть импортного сегмента у Кала-Ранта и AquaGen в средне-малых партиях, где скорость и сервис важнее премиум-генетики.
A17: УЗВ промышленные — высокий тех. барьер (5/5). Стратегия — не делать самим, а стать дистрибутором/интегратором лучших зарубежных решений.

Sheet 10_Бенчмарк_стран
A1: 10. Бенчмарк зарубежных рынков-эталонов: Норвегия / ЕС / США / Турция / Китай
A2: Цель: вытащить лучшие практики и определить, что можно перенести в РФ. Метод — структурированное сравнение.
A4: Страна | B4: Объём аквакультуры (≈) | C4: Ключевые виды | D4: Технологии-флагманы | E4: Что заимствовать MirAqua | F4: Барьер для переноса | G4: Приоритет (1-5)
A5: Норвегия | B5: 1.5+ млн т/год лосось+форель | C5: Атлантический лосось, форель | D5: Морские садки, селекция (AquaGen, Benchmark), функциональные корма (Skretting) | E5: Селекция икры (IPN-устойчивость), цифровизация фермы (мониторинг, ML-прогноз роста) | F5: Санкции/доступ к технологиям; высокая стоимость лицензий | G5: 5
A6: ЕС (Греция, Италия) | B6: ~600 тыс. т сибас/дорадо | C6: Сибас, дорадо, форель | D6: Полносистемная продуктовая интеграция (от мальков до сетей розницы), СПС-маркетинг | E6: Модель «продукт+рецепт+бренд» — повышение маржи через брендирование | F6: Логистика, отличия в потреб. предпочтениях | G6: 3
A7: США | B7: ~600 тыс. т (с креветкой и устрицей) | C7: Форель (Riverence), сом, устрицы | D7: УЗВ-проекты под лосось (Atlantic Sapphire), компьютерное зрение в кормораздаче | E7: УЗВ для регионов без природных условий — РФ потенциал большой | F7: CAPEX и компетенции по эксплуатации УЗВ | G7: 5
A8: Турция | B8: ~510 тыс. т аквакультуры | C8: Форель радужная (мировой топ-3 экспортёр) | D8: Низкая себестоимость, фокус на экспорт в СНГ и ЕС, плотные форелевые фермы | E8: Сценарии низкосебестоимостной форели, экспортные модели в страны СНГ | F8: Климатические условия частично воспроизводимы в южных регионах РФ | G8: 4
A9: Китай | B9: ~50+ млн т (всё аквакультура) | C9: Карповые, тилапия, рост лосось/форель в УЗВ | D9: Массовое внедрение УЗВ, IoT-датчики качества воды, государственные программы | E9: Системы IoT-мониторинга (датчики O₂, pH, температуры) — недорогие альтернативы Skretting/AKVA | F9: Языковой барьер, сертификация, репутация качества | G9: 4
A11: Что делаем с этим бенчмарком
A12: Обновляем раз в квартал (короткий ресёрч-отчёт на 2-3 страницы по странам с самым высоким приоритетом).
A13: Связываем выводы с листом 09 «Импортозамещение»: если технология «to learn from» совпадает с GO-нишей — это сигнал в продуктовый комитет.
A14: По каждой стране ведём «папку источников» (annual reports Mowi/Skretting, IntraFish, Undercurrent News, FAO SOFIA). Это и есть основа квартального обзора.

Sheet 11_Дашборд
A1: 11. Дашборд для коммерческого директора
A2: KPI-сводка по бизнес-юниту MirAqua. Все цифры — формулы из листов 03, 06, 09.
A4: Выручка, ₽/год | C4: Валовая прибыль, ₽/год | E4: Средняя маржа % | G4: Доля A-классов в выручке
A5: =SUM('06_Юнит_экономика'!G5:G10) -> 44373200 | C5: =SUM('06_Юнит_экономика'!H5:H10) -> 14029600 | E5: =AVERAGE('06_Юнит_экономика'!E5:E10) -> 0.33803345 | G5: =SUMIF('03_ABC_анализ'!G5:G19,"A",'03_ABC_анализ'!D5:D19)/SUM('03_ABC_анализ'!D5:D19) -> 0.75388027
A8: Топ-5 SKU по выручке (auto)
A9: # | B9: SKU | C9: Выручка, ₽ | D9: Доля % | E9: Накопит. % | F9: Класс ABC | G9: Категория | H9: Действие
A10: 1 | B10: ='03_ABC_анализ'!B5 -> Икра форелевая 100К партия (фермы) | C10: ='03_ABC_анализ'!D5 -> 18500000 | D10: ='03_ABC_анализ'!E5 -> 0.22788864 | E10: ='03_ABC_анализ'!F5 -> 0.22788864 | F10: ='03_ABC_анализ'!G5 -> A | G10: ='03_ABC_анализ'!C5 -> Икра | H10: =IF(F10="A","Защищать ассортимент",IF(F10="B","Поддерживать","Пересмотр")) -> Защищать ассортимент
A11: 2 | B11: ='03_ABC_анализ'!B6 -> Малёк форели 3-5г, оптом | C11: ='03_ABC_анализ'!D6 -> 14200000 | D11: ='03_ABC_анализ'!E6 -> 0.17491993 | E11: ='03_ABC_анализ'!F6 -> 0.40280857 | F11: ='03_ABC_анализ'!G6 -> A | G11: ='03_ABC_анализ'!C6 -> Малёк | H11: =IF(F11="A","Защищать ассортимент",IF(F11="B","Поддерживать","Пересмотр")) -> Защищать ассортимент
A12: 3 | B12: ='03_ABC_анализ'!B7 -> Товарная форель 1-1.5 кг (сети) | C12: ='03_ABC_анализ'!D7 -> 11800000 | D12: ='03_ABC_анализ'!E7 -> 0.145356 | E12: ='03_ABC_анализ'!F7 -> 0.54816457 | F12: ='03_ABC_анализ'!G7 -> A | G12: ='03_ABC_анализ'!C7 -> Товарная | H12: =IF(F12="A","Защищать ассортимент",IF(F12="B","Поддерживать","Пересмотр")) -> Защищать ассортимент
A13: 4 | B13: ='03_ABC_анализ'!B8 -> Икра форелевая 50К партия (средние фермы) | C13: ='03_ABC_анализ'!D8 -> 9300000 | D13: ='03_ABC_анализ'!E8 -> 0.11456024 | E13: ='03_ABC_анализ'!F8 -> 0.66272481 | F13: ='03_ABC_анализ'!G8 -> A | G13: ='03_ABC_анализ'!C8 -> Икра | H13: =IF(F13="A","Защищать ассортимент",IF(F13="B","Поддерживать","Пересмотр")) -> Защищать ассортимент
A14: 5 | B14: ='03_ABC_анализ'!B9 -> Малёк форели 5-10г, оптом | C14: ='03_ABC_анализ'!D9 -> 7400000 | D14: ='03_ABC_анализ'!E9 -> 0.091155457 | E14: ='03_ABC_анализ'!F9 -> 0.75388027 | F14: ='03_ABC_анализ'!G9 -> A | G14: ='03_ABC_анализ'!C9 -> Малёк | H14: =IF(F14="A","Защищать ассортимент",IF(F14="B","Поддерживать","Пересмотр")) -> Защищать ассортимент
A16: Импортозамещение: топ-3 ниши с приоритетом GO
A17: # | B17: Сегмент | C17: Объём рынка ₽ | D17: Доля импорта | E17: Наценка импорта | F17: Приоритет | G17: Действие
A18: 1 | B18: ='09_Импортозамещение'!A7 -> Корма стартовые (хетчеринг) | C18: ='09_Импортозамещение'!B7 -> 2400000000 | D18: ='09_Импортозамещение'!C7 -> 0.75 | E18: ='09_Импортозамещение'!E7 -> 1.22 | F18: ='09_Импортозамещение'!G7 -> 439.2 | G18: ='09_Импортозамещение'!H7 -> WAIT: проработать партнёрство
A19: 2 | B19: ='09_Импортозамещение'!A8 -> Корма продукционные | C19: ='09_Импортозамещение'!B8 -> 7800000000 | D19: ='09_Импортозамещение'!C8 -> 0.65 | E19: ='09_Импортозамещение'!E8 -> 1.15 | F19: ='09_Импортозамещение'!G8 -> 1457.625 | G19: ='09_Импортозамещение'!H8 -> GO: целевая ниша
A20: 3 | B20: ='09_Импортозамещение'!A10 -> УЗВ-оборудование, промышленные | C20: ='09_Импортозамещение'!B10 -> 2500000000 | D20: ='09_Импортозамещение'!C10 -> 0.85 | E20: ='09_Импортозамещение'!E10 -> 1.25 | F20: ='09_Импортозамещение'!G10 -> 531.25 | G20: ='09_Импортозамещение'!H10 -> GO: целевая ниша
A40: Этот лист и есть «отчёт коммерческому директору». В реальной работе сюда же подключаются Power Query / Power BI / DataLens к свежим данным.
